[
 {
  "id": "9",
  "name": "HS Bochum SolarCar-Team",
  "number": 11,
  "car_name": "Sun Riser",
  "country": "de",
  "class_id": 6,
  "lat": -19.33067,
  "lng": 134.18999,
  "gps_when": "2015-10-19 06:30:43",
  "dist_darwin": 842.764,
  "dist_adelaide": 1786.372,
  "gps_age": "13 mins 57 secs"
 },
 {
  "id": "9",
  "name": "HS Bochum SolarCar-Team",
  "number": 11,
  "car_name": "Sun Riser",
  "country": "de",
  "class_id": 6,
  "lat": -19.65753,
  "lng": 134.1884,
  "gps_when": "2015-10-19 08:40:36",
  "dist_darwin": 875.589,
  "dist_adelaide": 1751.065
 },
 {
  "id": "9",
  "name": "HS Bochum SolarCar-Team",
  "number": 11,
  "car_name": "Sun Riser",
  "country": "de",
  "class_id": 6,
  "lat": -19.63857,
  "lng": 134.19278,
  "gps_when": "2015-10-19 09:31:00",
  "dist_darwin": 873.865,
  "dist_adelaide": 1753.008
 },
 {
  "id": "9",
  "name": "HS Bochum SolarCar-Team",
  "number": 11,
  "car_name": "Sun Riser",
  "country": "de",
  "class_id": 6,
  "lat": -19.63834,
  "lng": 134.19308,
  "gps_when": "2015-10-19 09:40:26",
  "dist_darwin": 873.855,
  "dist_adelaide": 1753.026
 },
 {
  "id": "9",
  "name": "HS Bochum SolarCar-Team",
  "number": 11,
  "car_name": "Sun Riser",
  "country": "de",
  "class_id": 6,
  "lat": -19.63831,
  "lng": 134.19304,
  "gps_when": "2015-10-19 09:50:26",
  "dist_darwin": 873.85,
  "dist_adelaide": 1753.03
 },
 {
  "id": "9",
  "name": "HS Bochum SolarCar-Team",
  "number": 11,
  "car_name": "Sun Riser",
  "country": "de",
  "class_id": 6,
  "lat": -19.63829,
  "lng": 134.19302,
  "gps_when": "2015-10-19 10:00:58",
  "dist_darwin": 873.847,
  "dist_adelaide": 1753.032
 },
 {
  "id": "9",
  "name": "HS Bochum SolarCar-Team",
  "number": 11,
  "car_name": "Sun Riser",
  "country": "de",
  "class_id": 6,
  "lat": -19.63858,
  "lng": 134.19283,
  "gps_when": "2015-10-19 10:22:12",
  "dist_darwin": 873.868,
  "dist_adelaide": 1753.006
 },
 {
  "id": "9",
  "name": "HS Bochum SolarCar-Team",
  "number": 11,
  "car_name": "Sun Riser",
  "country": "de",
  "class_id": 6,
  "lat": -19.63858,
  "lng": 134.19283,
  "gps_when": "2015-10-19 10:30:23",
  "dist_darwin": 873.868,
  "dist_adelaide": 1753.006
 },
 {
  "id": "9",
  "name": "HS Bochum SolarCar-Team",
  "number": 11,
  "car_name": "Sun Riser",
  "country": "de",
  "class_id": 6,
  "lat": -19.63855,
  "lng": 134.19284,
  "gps_when": "2015-10-19 10:40:23",
  "dist_darwin": 873.865,
  "dist_adelaide": 1753.009
 },
 {
  "id": "9",
  "name": "HS Bochum SolarCar-Team",
  "number": 11,
  "car_name": "Sun Riser",
  "country": "de",
  "class_id": 6,
  "lat": -19.63855,
  "lng": 134.19283,
  "gps_when": "2015-10-19 10:50:26",
  "dist_darwin": 873.865,
  "dist_adelaide": 1753.009
 },
 {
  "id": "9",
  "name": "HS Bochum SolarCar-Team",
  "number": 11,
  "car_name": "Sun Riser",
  "country": "de",
  "class_id": 6,
  "lat": -19.63853,
  "lng": 134.19283,
  "gps_when": "2015-10-19 11:00:22",
  "dist_darwin": 873.863,
  "dist_adelaide": 1753.011
 },
 {
  "id": "9",
  "name": "HS Bochum SolarCar-Team",
  "number": 11,
  "car_name": "Sun Riser",
  "country": "de",
  "class_id": 6,
  "lat": -19.6386,
  "lng": 134.19284,
  "gps_when": "2015-10-19 11:10:21",
  "dist_darwin": 873.871,
  "dist_adelaide": 1753.003
 },
 {
  "id": "9",
  "name": "HS Bochum SolarCar-Team",
  "number": 11,
  "car_name": "Sun Riser",
  "country": "de",
  "class_id": 6,
  "lat": -19.63858,
  "lng": 134.19281,
  "gps_when": "2015-10-19 11:20:21",
  "dist_darwin": 873.867,
  "dist_adelaide": 1753.006
 },
 {
  "id": "9",
  "name": "HS Bochum SolarCar-Team",
  "number": 11,
  "car_name": "Sun Riser",
  "country": "de",
  "class_id": 6,
  "lat": -19.63857,
  "lng": 134.19283,
  "gps_when": "2015-10-19 11:30:20",
  "dist_darwin": 873.867,
  "dist_adelaide": 1753.007
 },
 {
  "id": "9",
  "name": "HS Bochum SolarCar-Team",
  "number": 11,
  "car_name": "Sun Riser",
  "country": "de",
  "class_id": 6,
  "lat": -19.65399,
  "lng": 134.18845,
  "gps_when": "2015-10-19 11:40:23",
  "dist_darwin": 875.234,
  "dist_adelaide": 1751.447
 },
 {
  "id": "9",
  "name": "HS Bochum SolarCar-Team",
  "number": 11,
  "car_name": "Sun Riser",
  "country": "de",
  "class_id": 6,
  "lat": -19.63852,
  "lng": 134.19278,
  "gps_when": "2015-10-19 11:50:22",
  "dist_darwin": 873.86,
  "dist_adelaide": 1753.013
 },
 {
  "id": "9",
  "name": "HS Bochum SolarCar-Team",
  "number": 11,
  "car_name": "Sun Riser",
  "country": "de",
  "class_id": 6,
  "lat": -19.63855,
  "lng": 134.19281,
  "gps_when": "2015-10-19 12:00:22",
  "dist_darwin": 873.864,
  "dist_adelaide": 1753.009
 },
 {
  "id": "9",
  "name": "HS Bochum SolarCar-Team",
  "number": 11,
  "car_name": "Sun Riser",
  "country": "de",
  "class_id": 6,
  "lat": -19.63857,
  "lng": 134.19284,
  "gps_when": "2015-10-19 12:10:21",
  "dist_darwin": 873.867,
  "dist_adelaide": 1753.007
 },
 {
  "id": "9",
  "name": "HS Bochum SolarCar-Team",
  "number": 11,
  "car_name": "Sun Riser",
  "country": "de",
  "class_id": 6,
  "lat": -19.63853,
  "lng": 134.19278,
  "gps_when": "2015-10-19 12:30:17",
  "dist_darwin": 873.861,
  "dist_adelaide": 1753.012
 },
 {
  "id": "9",
  "name": "HS Bochum SolarCar-Team",
  "number": 11,
  "car_name": "Sun Riser",
  "country": "de",
  "class_id": 6,
  "lat": -19.63853,
  "lng": 134.19283,
  "gps_when": "2015-10-19 12:40:17",
  "dist_darwin": 873.863,
  "dist_adelaide": 1753.011
 },
 {
  "id": "9",
  "name": "HS Bochum SolarCar-Team",
  "number": 11,
  "car_name": "Sun Riser",
  "country": "de",
  "class_id": 6,
  "lat": -19.63852,
  "lng": 134.19281,
  "gps_when": "2015-10-19 12:50:16",
  "dist_darwin": 873.861,
  "dist_adelaide": 1753.013
 },
 {
  "id": "9",
  "name": "HS Bochum SolarCar-Team",
  "number": 11,
  "car_name": "Sun Riser",
  "country": "de",
  "class_id": 6,
  "lat": -19.63852,
  "lng": 134.19276,
  "gps_when": "2015-10-19 13:00:18",
  "dist_darwin": 873.859,
  "dist_adelaide": 1753.014
 },
 {
  "id": "9",
  "name": "HS Bochum SolarCar-Team",
  "number": 11,
  "car_name": "Sun Riser",
  "country": "de",
  "class_id": 6,
  "lat": -19.63853,
  "lng": 134.19281,
  "gps_when": "2015-10-19 13:10:15",
  "dist_darwin": 873.862,
  "dist_adelaide": 1753.012
 },
 {
  "id": "9",
  "name": "HS Bochum SolarCar-Team",
  "number": 11,
  "car_name": "Sun Riser",
  "country": "de",
  "class_id": 6,
  "lat": -19.6385,
  "lng": 134.19284,
  "gps_when": "2015-10-19 13:20:17",
  "dist_darwin": 873.86,
  "dist_adelaide": 1753.014
 },
 {
  "id": "9",
  "name": "HS Bochum SolarCar-Team",
  "number": 11,
  "car_name": "Sun Riser",
  "country": "de",
  "class_id": 6,
  "lat": -19.63852,
  "lng": 134.1927,
  "gps_when": "2015-10-19 13:30:17",
  "dist_darwin": 873.856,
  "dist_adelaide": 1753.015
 },
 {
  "id": "9",
  "name": "HS Bochum SolarCar-Team",
  "number": 11,
  "car_name": "Sun Riser",
  "country": "de",
  "class_id": 6,
  "lat": -19.6385,
  "lng": 134.19278,
  "gps_when": "2015-10-19 13:40:16",
  "dist_darwin": 873.858,
  "dist_adelaide": 1753.016
 },
 {
  "id": "9",
  "name": "HS Bochum SolarCar-Team",
  "number": 11,
  "car_name": "Sun Riser",
  "country": "de",
  "class_id": 6,
  "lat": -19.63852,
  "lng": 134.19283,
  "gps_when": "2015-10-19 13:50:16",
  "dist_darwin": 873.862,
  "dist_adelaide": 1753.012
 },
 {
  "id": "9",
  "name": "HS Bochum SolarCar-Team",
  "number": 11,
  "car_name": "Sun Riser",
  "country": "de",
  "class_id": 6,
  "lat": -19.6385,
  "lng": 134.19276,
  "gps_when": "2015-10-19 14:00:42",
  "dist_darwin": 873.857,
  "dist_adelaide": 1753.016
 },
 {
  "id": "9",
  "name": "HS Bochum SolarCar-Team",
  "number": 11,
  "car_name": "Sun Riser",
  "country": "de",
  "class_id": 6,
  "lat": -19.63849,
  "lng": 134.19281,
  "gps_when": "2015-10-19 14:10:12",
  "dist_darwin": 873.858,
  "dist_adelaide": 1753.016
 },
 {
  "id": "9",
  "name": "HS Bochum SolarCar-Team",
  "number": 11,
  "car_name": "Sun Riser",
  "country": "de",
  "class_id": 6,
  "lat": -19.63849,
  "lng": 134.19273,
  "gps_when": "2015-10-19 14:20:14",
  "dist_darwin": 873.855,
  "dist_adelaide": 1753.018
 },
 {
  "id": "9",
  "name": "HS Bochum SolarCar-Team",
  "number": 11,
  "car_name": "Sun Riser",
  "country": "de",
  "class_id": 6,
  "lat": -19.63849,
  "lng": 134.19283,
  "gps_when": "2015-10-19 14:30:11",
  "dist_darwin": 873.859,
  "dist_adelaide": 1753.015
 },
 {
  "id": "9",
  "name": "HS Bochum SolarCar-Team",
  "number": 11,
  "car_name": "Sun Riser",
  "country": "de",
  "class_id": 6,
  "lat": -19.63852,
  "lng": 134.19281,
  "gps_when": "2015-10-19 14:40:10",
  "dist_darwin": 873.861,
  "dist_adelaide": 1753.013
 },
 {
  "id": "9",
  "name": "HS Bochum SolarCar-Team",
  "number": 11,
  "car_name": "Sun Riser",
  "country": "de",
  "class_id": 6,
  "lat": -19.63852,
  "lng": 134.19278,
  "gps_when": "2015-10-19 14:50:12",
  "dist_darwin": 873.86,
  "dist_adelaide": 1753.013
 },
 {
  "id": "9",
  "name": "HS Bochum SolarCar-Team",
  "number": 11,
  "car_name": "Sun Riser",
  "country": "de",
  "class_id": 6,
  "lat": -19.63852,
  "lng": 134.19278,
  "gps_when": "2015-10-19 15:00:12",
  "dist_darwin": 873.86,
  "dist_adelaide": 1753.013
 },
 {
  "id": "9",
  "name": "HS Bochum SolarCar-Team",
  "number": 11,
  "car_name": "Sun Riser",
  "country": "de",
  "class_id": 6,
  "lat": -19.63855,
  "lng": 134.19278,
  "gps_when": "2015-10-19 15:10:26",
  "dist_darwin": 873.863,
  "dist_adelaide": 1753.01
 },
 {
  "id": "9",
  "name": "HS Bochum SolarCar-Team",
  "number": 11,
  "car_name": "Sun Riser",
  "country": "de",
  "class_id": 6,
  "lat": -19.63852,
  "lng": 134.19283,
  "gps_when": "2015-10-19 15:20:07",
  "dist_darwin": 873.862,
  "dist_adelaide": 1753.012
 },
 {
  "id": "9",
  "name": "HS Bochum SolarCar-Team",
  "number": 11,
  "car_name": "Sun Riser",
  "country": "de",
  "class_id": 6,
  "lat": -19.63847,
  "lng": 134.19276,
  "gps_when": "2015-10-19 15:30:40",
  "dist_darwin": 873.854,
  "dist_adelaide": 1753.019
 },
 {
  "id": "9",
  "name": "HS Bochum SolarCar-Team",
  "number": 11,
  "car_name": "Sun Riser",
  "country": "de",
  "class_id": 6,
  "lat": -19.63852,
  "lng": 134.19284,
  "gps_when": "2015-10-19 15:40:10",
  "dist_darwin": 873.862,
  "dist_adelaide": 1753.012
 },
 {
  "id": "9",
  "name": "HS Bochum SolarCar-Team",
  "number": 11,
  "car_name": "Sun Riser",
  "country": "de",
  "class_id": 6,
  "lat": -19.63852,
  "lng": 134.19278,
  "gps_when": "2015-10-19 15:50:09",
  "dist_darwin": 873.86,
  "dist_adelaide": 1753.013
 },
 {
  "id": "9",
  "name": "HS Bochum SolarCar-Team",
  "number": 11,
  "car_name": "Sun Riser",
  "country": "de",
  "class_id": 6,
  "lat": -19.63844,
  "lng": 134.19278,
  "gps_when": "2015-10-19 16:00:06",
  "dist_darwin": 873.852,
  "dist_adelaide": 1753.022
 },
 {
  "id": "9",
  "name": "HS Bochum SolarCar-Team",
  "number": 11,
  "car_name": "Sun Riser",
  "country": "de",
  "class_id": 6,
  "lat": -19.63853,
  "lng": 134.19281,
  "gps_when": "2015-10-19 16:10:11",
  "dist_darwin": 873.862,
  "dist_adelaide": 1753.012
 },
 {
  "id": "9",
  "name": "HS Bochum SolarCar-Team",
  "number": 11,
  "car_name": "Sun Riser",
  "country": "de",
  "class_id": 6,
  "lat": -19.63853,
  "lng": 134.19284,
  "gps_when": "2015-10-19 16:20:08",
  "dist_darwin": 873.863,
  "dist_adelaide": 1753.011
 },
 {
  "id": "9",
  "name": "HS Bochum SolarCar-Team",
  "number": 11,
  "car_name": "Sun Riser",
  "country": "de",
  "class_id": 6,
  "lat": -19.63843,
  "lng": 134.19278,
  "gps_when": "2015-10-19 16:30:07",
  "dist_darwin": 873.851,
  "dist_adelaide": 1753.023
 },
 {
  "id": "9",
  "name": "HS Bochum SolarCar-Team",
  "number": 11,
  "car_name": "Sun Riser",
  "country": "de",
  "class_id": 6,
  "lat": -19.63849,
  "lng": 134.19276,
  "gps_when": "2015-10-19 16:41:00",
  "dist_darwin": 873.856,
  "dist_adelaide": 1753.017
 },
 {
  "id": "9",
  "name": "HS Bochum SolarCar-Team",
  "number": 11,
  "car_name": "Sun Riser",
  "country": "de",
  "class_id": 6,
  "lat": -19.63852,
  "lng": 134.19284,
  "gps_when": "2015-10-19 16:50:03",
  "dist_darwin": 873.862,
  "dist_adelaide": 1753.012
 },
 {
  "id": "9",
  "name": "HS Bochum SolarCar-Team",
  "number": 11,
  "car_name": "Sun Riser",
  "country": "de",
  "class_id": 6,
  "lat": -19.63852,
  "lng": 134.19281,
  "gps_when": "2015-10-19 17:00:06",
  "dist_darwin": 873.861,
  "dist_adelaide": 1753.013
 },
 {
  "id": "9",
  "name": "HS Bochum SolarCar-Team",
  "number": 11,
  "car_name": "Sun Riser",
  "country": "de",
  "class_id": 6,
  "lat": -19.63852,
  "lng": 134.19281,
  "gps_when": "2015-10-19 17:10:02",
  "dist_darwin": 873.861,
  "dist_adelaide": 1753.013
 },
 {
  "id": "9",
  "name": "HS Bochum SolarCar-Team",
  "number": 11,
  "car_name": "Sun Riser",
  "country": "de",
  "class_id": 6,
  "lat": -19.63853,
  "lng": 134.19278,
  "gps_when": "2015-10-19 17:20:04",
  "dist_darwin": 873.861,
  "dist_adelaide": 1753.012
 },
 {
  "id": "9",
  "name": "HS Bochum SolarCar-Team",
  "number": 11,
  "car_name": "Sun Riser",
  "country": "de",
  "class_id": 6,
  "lat": -19.63853,
  "lng": 134.19278,
  "gps_when": "2015-10-19 17:30:16",
  "dist_darwin": 873.861,
  "dist_adelaide": 1753.012
 },
 {
  "id": "9",
  "name": "HS Bochum SolarCar-Team",
  "number": 11,
  "car_name": "Sun Riser",
  "country": "de",
  "class_id": 6,
  "lat": -19.63849,
  "lng": 134.19284,
  "gps_when": "2015-10-19 17:40:03",
  "dist_darwin": 873.859,
  "dist_adelaide": 1753.015
 },
 {
  "id": "9",
  "name": "HS Bochum SolarCar-Team",
  "number": 11,
  "car_name": "Sun Riser",
  "country": "de",
  "class_id": 6,
  "lat": -19.63853,
  "lng": 134.19278,
  "gps_when": "2015-10-19 17:50:03",
  "dist_darwin": 873.861,
  "dist_adelaide": 1753.012
 },
 {
  "id": "9",
  "name": "HS Bochum SolarCar-Team",
  "number": 11,
  "car_name": "Sun Riser",
  "country": "de",
  "class_id": 6,
  "lat": -19.63852,
  "lng": 134.19278,
  "gps_when": "2015-10-19 17:59:59",
  "dist_darwin": 873.86,
  "dist_adelaide": 1753.013
 },
 {
  "id": "9",
  "name": "HS Bochum SolarCar-Team",
  "number": 11,
  "car_name": "Sun Riser",
  "country": "de",
  "class_id": 6,
  "lat": -19.63852,
  "lng": 134.19278,
  "gps_when": "2015-10-19 18:10:02",
  "dist_darwin": 873.86,
  "dist_adelaide": 1753.013
 },
 {
  "id": "9",
  "name": "HS Bochum SolarCar-Team",
  "number": 11,
  "car_name": "Sun Riser",
  "country": "de",
  "class_id": 6,
  "lat": -19.63846,
  "lng": 134.19292,
  "gps_when": "2015-10-19 18:20:04",
  "dist_darwin": 873.86,
  "dist_adelaide": 1753.016
 },
 {
  "id": "9",
  "name": "HS Bochum SolarCar-Team",
  "number": 11,
  "car_name": "Sun Riser",
  "country": "de",
  "class_id": 6,
  "lat": -19.63847,
  "lng": 134.19278,
  "gps_when": "2015-10-19 19:09:58",
  "dist_darwin": 873.855,
  "dist_adelaide": 1753.019
 },
 {
  "id": "9",
  "name": "HS Bochum SolarCar-Team",
  "number": 11,
  "car_name": "Sun Riser",
  "country": "de",
  "class_id": 6,
  "lat": -19.63852,
  "lng": 134.19278,
  "gps_when": "2015-10-19 19:19:57",
  "dist_darwin": 873.86,
  "dist_adelaide": 1753.013
 },
 {
  "id": "9",
  "name": "HS Bochum SolarCar-Team",
  "number": 11,
  "car_name": "Sun Riser",
  "country": "de",
  "class_id": 6,
  "lat": -19.6385,
  "lng": 134.19278,
  "gps_when": "2015-10-19 19:29:57",
  "dist_darwin": 873.858,
  "dist_adelaide": 1753.016
 },
 {
  "id": "9",
  "name": "HS Bochum SolarCar-Team",
  "number": 11,
  "car_name": "Sun Riser",
  "country": "de",
  "class_id": 6,
  "lat": -19.63852,
  "lng": 134.19281,
  "gps_when": "2015-10-19 19:40:18",
  "dist_darwin": 873.861,
  "dist_adelaide": 1753.013
 },
 {
  "id": "9",
  "name": "HS Bochum SolarCar-Team",
  "number": 11,
  "car_name": "Sun Riser",
  "country": "de",
  "class_id": 6,
  "lat": -19.6385,
  "lng": 134.19278,
  "gps_when": "2015-10-19 19:51:02",
  "dist_darwin": 873.858,
  "dist_adelaide": 1753.016
 },
 {
  "id": "9",
  "name": "HS Bochum SolarCar-Team",
  "number": 11,
  "car_name": "Sun Riser",
  "country": "de",
  "class_id": 6,
  "lat": -19.63832,
  "lng": 134.19278,
  "gps_when": "2015-10-19 19:59:56",
  "dist_darwin": 873.84,
  "dist_adelaide": 1753.035
 },
 {
  "id": "9",
  "name": "HS Bochum SolarCar-Team",
  "number": 11,
  "car_name": "Sun Riser",
  "country": "de",
  "class_id": 6,
  "lat": -19.63869,
  "lng": 134.19235,
  "gps_when": "2015-10-19 20:09:55",
  "dist_darwin": 873.858,
  "dist_adelaide": 1753.005
 },
 {
  "id": "9",
  "name": "HS Bochum SolarCar-Team",
  "number": 11,
  "car_name": "Sun Riser",
  "country": "de",
  "class_id": 6,
  "lat": -19.65739,
  "lng": 134.18819,
  "gps_when": "2015-10-19 20:19:55",
  "dist_darwin": 875.566,
  "dist_adelaide": 1751.085
 },
 {
  "id": "9",
  "name": "HS Bochum SolarCar-Team",
  "number": 11,
  "car_name": "Sun Riser",
  "country": "de",
  "class_id": 6,
  "lat": -19.65746,
  "lng": 134.18851,
  "gps_when": "2015-10-19 20:29:54",
  "dist_darwin": 875.587,
  "dist_adelaide": 1751.07
 },
 {
  "id": "9",
  "name": "HS Bochum SolarCar-Team",
  "number": 11,
  "car_name": "Sun Riser",
  "country": "de",
  "class_id": 6,
  "lat": -19.65749,
  "lng": 134.18855,
  "gps_when": "2015-10-19 20:39:53",
  "dist_darwin": 875.592,
  "dist_adelaide": 1751.066
 },
 {
  "id": "9",
  "name": "HS Bochum SolarCar-Team",
  "number": 11,
  "car_name": "Sun Riser",
  "country": "de",
  "class_id": 6,
  "lat": -19.6575,
  "lng": 134.18855,
  "gps_when": "2015-10-19 20:49:53",
  "dist_darwin": 875.593,
  "dist_adelaide": 1751.065
 },
 {
  "id": "9",
  "name": "HS Bochum SolarCar-Team",
  "number": 11,
  "car_name": "Sun Riser",
  "country": "de",
  "class_id": 6,
  "lat": -19.65752,
  "lng": 134.18849,
  "gps_when": "2015-10-19 20:59:52",
  "dist_darwin": 875.592,
  "dist_adelaide": 1751.064
 },
 {
  "id": "9",
  "name": "HS Bochum SolarCar-Team",
  "number": 11,
  "car_name": "Sun Riser",
  "country": "de",
  "class_id": 6,
  "lat": -19.65741,
  "lng": 134.18861,
  "gps_when": "2015-10-19 21:10:33",
  "dist_darwin": 875.586,
  "dist_adelaide": 1751.073
 },
 {
  "id": "9",
  "name": "HS Bochum SolarCar-Team",
  "number": 11,
  "car_name": "Sun Riser",
  "country": "de",
  "class_id": 6,
  "lat": -19.65739,
  "lng": 134.18861,
  "gps_when": "2015-10-19 21:20:00",
  "dist_darwin": 875.584,
  "dist_adelaide": 1751.075
 },
 {
  "id": "9",
  "name": "HS Bochum SolarCar-Team",
  "number": 11,
  "car_name": "Sun Riser",
  "country": "de",
  "class_id": 6,
  "lat": -19.65752,
  "lng": 134.18851,
  "gps_when": "2015-10-19 21:29:54",
  "dist_darwin": 875.593,
  "dist_adelaide": 1751.064
 },
 {
  "id": "9",
  "name": "HS Bochum SolarCar-Team",
  "number": 11,
  "car_name": "Sun Riser",
  "country": "de",
  "class_id": 6,
  "lat": -19.65752,
  "lng": 134.18851,
  "gps_when": "2015-10-19 21:39:50",
  "dist_darwin": 875.593,
  "dist_adelaide": 1751.064
 },
 {
  "id": "9",
  "name": "HS Bochum SolarCar-Team",
  "number": 11,
  "car_name": "Sun Riser",
  "country": "de",
  "class_id": 6,
  "lat": -19.65749,
  "lng": 134.18855,
  "gps_when": "2015-10-19 21:50:02",
  "dist_darwin": 875.592,
  "dist_adelaide": 1751.066
 },
 {
  "id": "9",
  "name": "HS Bochum SolarCar-Team",
  "number": 11,
  "car_name": "Sun Riser",
  "country": "de",
  "class_id": 6,
  "lat": -19.65749,
  "lng": 134.18855,
  "gps_when": "2015-10-19 22:00:01",
  "dist_darwin": 875.592,
  "dist_adelaide": 1751.066
 },
 {
  "id": "9",
  "name": "HS Bochum SolarCar-Team",
  "number": 11,
  "car_name": "Sun Riser",
  "country": "de",
  "class_id": 6,
  "lat": -19.65747,
  "lng": 134.18855,
  "gps_when": "2015-10-19 22:09:45",
  "dist_darwin": 875.59,
  "dist_adelaide": 1751.068
 },
 {
  "id": "9",
  "name": "HS Bochum SolarCar-Team",
  "number": 11,
  "car_name": "Sun Riser",
  "country": "de",
  "class_id": 6,
  "lat": -19.65747,
  "lng": 134.18854,
  "gps_when": "2015-10-19 22:19:48",
  "dist_darwin": 875.589,
  "dist_adelaide": 1751.068
 },
 {
  "id": "9",
  "name": "HS Bochum SolarCar-Team",
  "number": 11,
  "car_name": "Sun Riser",
  "country": "de",
  "class_id": 6,
  "lat": -19.6575,
  "lng": 134.18854,
  "gps_when": "2015-10-19 22:29:47",
  "dist_darwin": 875.592,
  "dist_adelaide": 1751.065
 },
 {
  "id": "9",
  "name": "HS Bochum SolarCar-Team",
  "number": 11,
  "car_name": "Sun Riser",
  "country": "de",
  "class_id": 6,
  "lat": -19.65762,
  "lng": 134.18861,
  "gps_when": "2015-10-19 22:33:10",
  "dist_darwin": 875.608,
  "dist_adelaide": 1751.05
 },
 {
  "id": "9",
  "name": "HS Bochum SolarCar-Team",
  "number": 11,
  "car_name": "Sun Riser",
  "country": "de",
  "class_id": 6,
  "lat": -19.68951,
  "lng": 134.17709,
  "gps_when": "2015-10-19 22:42:25",
  "dist_darwin": 878.333,
  "dist_adelaide": 1747.885
 },
 {
  "id": "9",
  "name": "HS Bochum SolarCar-Team",
  "number": 11,
  "car_name": "Sun Riser",
  "country": "de",
  "class_id": 6,
  "lat": -19.78267,
  "lng": 134.19626,
  "gps_when": "2015-10-19 22:52:27",
  "dist_darwin": 888.592,
  "dist_adelaide": 1737.351
 },
 {
  "id": "9",
  "name": "HS Bochum SolarCar-Team",
  "number": 11,
  "car_name": "Sun Riser",
  "country": "de",
  "class_id": 6,
  "lat": -19.87808,
  "lng": 134.20543,
  "gps_when": "2015-10-19 23:02:24",
  "dist_darwin": 898.659,
  "dist_adelaide": 1726.82
 },
 {
  "id": "9",
  "name": "HS Bochum SolarCar-Team",
  "number": 11,
  "car_name": "Sun Riser",
  "country": "de",
  "class_id": 6,
  "lat": -19.97411,
  "lng": 134.21539,
  "gps_when": "2015-10-19 23:12:29",
  "dist_darwin": 908.835,
  "dist_adelaide": 1716.204
 },
 {
  "id": "9",
  "name": "HS Bochum SolarCar-Team",
  "number": 11,
  "car_name": "Sun Riser",
  "country": "de",
  "class_id": 6,
  "lat": -20.06662,
  "lng": 134.20897,
  "gps_when": "2015-10-19 23:22:23",
  "dist_darwin": 917.98,
  "dist_adelaide": 1706.374
 },
 {
  "id": "9",
  "name": "HS Bochum SolarCar-Team",
  "number": 11,
  "car_name": "Sun Riser",
  "country": "de",
  "class_id": 6,
  "lat": -20.16109,
  "lng": 134.22112,
  "gps_when": "2015-10-19 23:32:25",
  "dist_darwin": 928.116,
  "dist_adelaide": 1695.876
 },
 {
  "id": "9",
  "name": "HS Bochum SolarCar-Team",
  "number": 11,
  "car_name": "Sun Riser",
  "country": "de",
  "class_id": 6,
  "lat": -20.25661,
  "lng": 134.2254,
  "gps_when": "2015-10-19 23:42:24",
  "dist_darwin": 938.046,
  "dist_adelaide": 1685.463
 },
 {
  "id": "9",
  "name": "HS Bochum SolarCar-Team",
  "number": 11,
  "car_name": "Sun Riser",
  "country": "de",
  "class_id": 6,
  "lat": -20.35155,
  "lng": 134.23697,
  "gps_when": "2015-10-19 23:52:21",
  "dist_darwin": 948.227,
  "dist_adelaide": 1674.931
 },
 {
  "id": "9",
  "name": "HS Bochum SolarCar-Team",
  "number": 11,
  "car_name": "Sun Riser",
  "country": "de",
  "class_id": 6,
  "lat": -20.44844,
  "lng": 134.24918,
  "gps_when": "2015-10-20 00:02:23",
  "dist_darwin": 958.642,
  "dist_adelaide": 1664.175
 },
 {
  "id": "9",
  "name": "HS Bochum SolarCar-Team",
  "number": 11,
  "car_name": "Sun Riser",
  "country": "de",
  "class_id": 6,
  "lat": -20.53996,
  "lng": 134.27338,
  "gps_when": "2015-10-20 00:12:23",
  "dist_darwin": 968.996,
  "dist_adelaide": 1653.698
 },
 {
  "id": "9",
  "name": "HS Bochum SolarCar-Team",
  "number": 11,
  "car_name": "Sun Riser",
  "country": "de",
  "class_id": 6,
  "lat": -20.61781,
  "lng": 134.21965,
  "gps_when": "2015-10-20 00:22:22",
  "dist_darwin": 974.861,
  "dist_adelaide": 1646.666
 },
 {
  "id": "9",
  "name": "HS Bochum SolarCar-Team",
  "number": 11,
  "car_name": "Sun Riser",
  "country": "de",
  "class_id": 6,
  "lat": -20.74315,
  "lng": 134.24402,
  "gps_when": "2015-10-20 00:35:19",
  "dist_darwin": 988.72,
  "dist_adelaide": 1632.543
 },
 {
  "id": "9",
  "name": "HS Bochum SolarCar-Team",
  "number": 11,
  "car_name": "Sun Riser",
  "country": "de",
  "class_id": 6,
  "lat": -20.83574,
  "lng": 134.2412,
  "gps_when": "2015-10-20 00:44:48",
  "dist_darwin": 998.158,
  "dist_adelaide": 1622.645
 },
 {
  "id": "9",
  "name": "HS Bochum SolarCar-Team",
  "number": 11,
  "car_name": "Sun Riser",
  "country": "de",
  "class_id": 6,
  "lat": -20.91101,
  "lng": 134.22215,
  "gps_when": "2015-10-20 00:52:42",
  "dist_darwin": 1005.204,
  "dist_adelaide": 1615.035
 },
 {
  "id": "9",
  "name": "HS Bochum SolarCar-Team",
  "number": 11,
  "car_name": "Sun Riser",
  "country": "de",
  "class_id": 6,
  "lat": -21.00951,
  "lng": 134.19434,
  "gps_when": "2015-10-20 01:03:03",
  "dist_darwin": 1014.355,
  "dist_adelaide": 1605.166
 },
 {
  "id": "9",
  "name": "HS Bochum SolarCar-Team",
  "number": 11,
  "car_name": "Sun Riser",
  "country": "de",
  "class_id": 6,
  "lat": -21.09872,
  "lng": 134.16901,
  "gps_when": "2015-10-20 01:12:23",
  "dist_darwin": 1022.676,
  "dist_adelaide": 1596.246
 },
 {
  "id": "9",
  "name": "HS Bochum SolarCar-Team",
  "number": 11,
  "car_name": "Sun Riser",
  "country": "de",
  "class_id": 6,
  "lat": -21.21181,
  "lng": 134.1369,
  "gps_when": "2015-10-20 01:24:10",
  "dist_darwin": 1033.277,
  "dist_adelaide": 1584.96
 },
 {
  "id": "9",
  "name": "HS Bochum SolarCar-Team",
  "number": 11,
  "car_name": "Sun Riser",
  "country": "de",
  "class_id": 6,
  "lat": -21.2863,
  "lng": 134.0699,
  "gps_when": "2015-10-20 01:33:48",
  "dist_darwin": 1038.672,
  "dist_adelaide": 1578.787
 },
 {
  "id": "9",
  "name": "HS Bochum SolarCar-Team",
  "number": 11,
  "car_name": "Sun Riser",
  "country": "de",
  "class_id": 6,
  "lat": -21.34943,
  "lng": 134.00516,
  "gps_when": "2015-10-20 01:42:15",
  "dist_darwin": 1043.042,
  "dist_adelaide": 1573.812
 },
 {
  "id": "9",
  "name": "HS Bochum SolarCar-Team",
  "number": 11,
  "car_name": "Sun Riser",
  "country": "de",
  "class_id": 6,
  "lat": -21.52885,
  "lng": 133.88922,
  "gps_when": "2015-10-20 02:03:02",
  "dist_darwin": 1058.055,
  "dist_adelaide": 1557.915
 },
 {
  "id": "9",
  "name": "HS Bochum SolarCar-Team",
  "number": 11,
  "car_name": "Sun Riser",
  "country": "de",
  "class_id": 6,
  "lat": -21.53096,
  "lng": 133.88889,
  "gps_when": "2015-10-20 02:12:16",
  "dist_darwin": 1058.266,
  "dist_adelaide": 1557.699
 },
 {
  "id": "9",
  "name": "HS Bochum SolarCar-Team",
  "number": 11,
  "car_name": "Sun Riser",
  "country": "de",
  "class_id": 6,
  "lat": -21.53098,
  "lng": 133.88892,
  "gps_when": "2015-10-20 02:22:16",
  "dist_darwin": 1058.27,
  "dist_adelaide": 1557.696
 },
 {
  "id": "9",
  "name": "HS Bochum SolarCar-Team",
  "number": 11,
  "car_name": "Sun Riser",
  "country": "de",
  "class_id": 6,
  "lat": -21.53098,
  "lng": 133.88896,
  "gps_when": "2015-10-20 02:32:18",
  "dist_darwin": 1058.271,
  "dist_adelaide": 1557.695
 },
 {
  "id": "9",
  "name": "HS Bochum SolarCar-Team",
  "number": 11,
  "car_name": "Sun Riser",
  "country": "de",
  "class_id": 6,
  "lat": -21.57283,
  "lng": 133.81154,
  "gps_when": "2015-10-20 02:42:24",
  "dist_darwin": 1060.217,
  "dist_adelaide": 1555.479
 },
 {
  "id": "9",
  "name": "HS Bochum SolarCar-Team",
  "number": 11,
  "car_name": "Sun Riser",
  "country": "de",
  "class_id": 6,
  "lat": -22.24011,
  "lng": 133.42511,
  "gps_when": "2015-10-20 04:02:59",
  "dist_darwin": 1120.364,
  "dist_adelaide": 1496.725
 },
 {
  "id": "9",
  "name": "HS Bochum SolarCar-Team",
  "number": 11,
  "car_name": "Sun Riser",
  "country": "de",
  "class_id": 6,
  "lat": -22.32243,
  "lng": 133.40302,
  "gps_when": "2015-10-20 04:12:10",
  "dist_darwin": 1128.655,
  "dist_adelaide": 1488.782
 },
 {
  "id": "9",
  "name": "HS Bochum SolarCar-Team",
  "number": 11,
  "car_name": "Sun Riser",
  "country": "de",
  "class_id": 6,
  "lat": -22.42178,
  "lng": 133.3632,
  "gps_when": "2015-10-20 04:22:06",
  "dist_darwin": 1138.36,
  "dist_adelaide": 1479.656
 },
 {
  "id": "9",
  "name": "HS Bochum SolarCar-Team",
  "number": 11,
  "car_name": "Sun Riser",
  "country": "de",
  "class_id": 6,
  "lat": -22.52565,
  "lng": 133.33014,
  "gps_when": "2015-10-20 04:32:06",
  "dist_darwin": 1148.757,
  "dist_adelaide": 1469.862
 },
 {
  "id": "9",
  "name": "HS Bochum SolarCar-Team",
  "number": 11,
  "car_name": "Sun Riser",
  "country": "de",
  "class_id": 6,
  "lat": -22.63535,
  "lng": 133.34747,
  "gps_when": "2015-10-20 04:42:09",
  "dist_darwin": 1161.022,
  "dist_adelaide": 1457.769
 },
 {
  "id": "9",
  "name": "HS Bochum SolarCar-Team",
  "number": 11,
  "car_name": "Sun Riser",
  "country": "de",
  "class_id": 6,
  "lat": -22.73883,
  "lng": 133.39168,
  "gps_when": "2015-10-20 04:52:08",
  "dist_darwin": 1173.266,
  "dist_adelaide": 1445.418
 },
 {
  "id": "9",
  "name": "HS Bochum SolarCar-Team",
  "number": 11,
  "car_name": "Sun Riser",
  "country": "de",
  "class_id": 6,
  "lat": -22.84258,
  "lng": 133.45018,
  "gps_when": "2015-10-20 05:02:05",
  "dist_darwin": 1185.892,
  "dist_adelaide": 1432.556
 },
 {
  "id": "9",
  "name": "HS Bochum SolarCar-Team",
  "number": 11,
  "car_name": "Sun Riser",
  "country": "de",
  "class_id": 6,
  "lat": -22.94633,
  "lng": 133.54021,
  "gps_when": "2015-10-20 05:12:04",
  "dist_darwin": 1199.312,
  "dist_adelaide": 1418.637
 },
 {
  "id": "9",
  "name": "HS Bochum SolarCar-Team",
  "number": 11,
  "car_name": "Sun Riser",
  "country": "de",
  "class_id": 6,
  "lat": -23.05695,
  "lng": 133.63527,
  "gps_when": "2015-10-20 05:22:09",
  "dist_darwin": 1213.634,
  "dist_adelaide": 1403.846
 },
 {
  "id": "9",
  "name": "HS Bochum SolarCar-Team",
  "number": 11,
  "car_name": "Sun Riser",
  "country": "de",
  "class_id": 6,
  "lat": -23.16534,
  "lng": 133.7281,
  "gps_when": "2015-10-20 05:32:03",
  "dist_darwin": 1227.692,
  "dist_adelaide": 1389.381
 },
 {
  "id": "9",
  "name": "HS Bochum SolarCar-Team",
  "number": 11,
  "car_name": "Sun Riser",
  "country": "de",
  "class_id": 6,
  "lat": -23.26926,
  "lng": 133.77704,
  "gps_when": "2015-10-20 05:42:06",
  "dist_darwin": 1240.137,
  "dist_adelaide": 1376.839
 },
 {
  "id": "9",
  "name": "HS Bochum SolarCar-Team",
  "number": 11,
  "car_name": "Sun Riser",
  "country": "de",
  "class_id": 6,
  "lat": -23.35664,
  "lng": 133.8053,
  "gps_when": "2015-10-20 05:52:02",
  "dist_darwin": 1250.263,
  "dist_adelaide": 1366.718
 },
 {
  "id": "9",
  "name": "HS Bochum SolarCar-Team",
  "number": 11,
  "car_name": "Sun Riser",
  "country": "de",
  "class_id": 6,
  "lat": -23.44441,
  "lng": 133.83395,
  "gps_when": "2015-10-20 06:02:01",
  "dist_darwin": 1260.44,
  "dist_adelaide": 1356.544
 },
 {
  "id": "9",
  "name": "HS Bochum SolarCar-Team",
  "number": 11,
  "car_name": "Sun Riser",
  "country": "de",
  "class_id": 6,
  "lat": -23.7088,
  "lng": 133.87506,
  "gps_when": "2015-10-20 06:32:48",
  "dist_darwin": 1289.904,
  "dist_adelaide": 1327.396
 },
 {
  "id": "9",
  "name": "HS Bochum SolarCar-Team",
  "number": 11,
  "car_name": "Sun Riser",
  "country": "de",
  "class_id": 6,
  "lat": -23.70886,
  "lng": 133.87506,
  "gps_when": "2015-10-20 06:42:02",
  "dist_darwin": 1289.911,
  "dist_adelaide": 1327.39
 },
 {
  "id": "9",
  "name": "HS Bochum SolarCar-Team",
  "number": 11,
  "car_name": "Sun Riser",
  "country": "de",
  "class_id": 6,
  "lat": -23.78889,
  "lng": 133.87892,
  "gps_when": "2015-10-20 22:45:24",
  "dist_darwin": 1298.608,
  "dist_adelaide": 1318.859
 },
 {
  "id": "9",
  "name": "HS Bochum SolarCar-Team",
  "number": 11,
  "car_name": "Sun Riser",
  "country": "de",
  "class_id": 6,
  "lat": -23.86522,
  "lng": 133.80096,
  "gps_when": "2015-10-20 22:55:20",
  "dist_darwin": 1304.823,
  "dist_adelaide": 1313.488
 },
 {
  "id": "9",
  "name": "HS Bochum SolarCar-Team",
  "number": 11,
  "car_name": "Sun Riser",
  "country": "de",
  "class_id": 6,
  "lat": -23.94881,
  "lng": 133.72372,
  "gps_when": "2015-10-20 23:05:23",
  "dist_darwin": 1311.918,
  "dist_adelaide": 1307.407
 },
 {
  "id": "9",
  "name": "HS Bochum SolarCar-Team",
  "number": 11,
  "car_name": "Sun Riser",
  "country": "de",
  "class_id": 6,
  "lat": -24.02618,
  "lng": 133.64368,
  "gps_when": "2015-10-20 23:15:22",
  "dist_darwin": 1318.355,
  "dist_adelaide": 1302.148
 },
 {
  "id": "9",
  "name": "HS Bochum SolarCar-Team",
  "number": 11,
  "car_name": "Sun Riser",
  "country": "de",
  "class_id": 6,
  "lat": -24.10526,
  "lng": 133.56105,
  "gps_when": "2015-10-20 23:25:19",
  "dist_darwin": 1324.997,
  "dist_adelaide": 1296.884
 },
 {
  "id": "9",
  "name": "HS Bochum SolarCar-Team",
  "number": 11,
  "car_name": "Sun Riser",
  "country": "de",
  "class_id": 6,
  "lat": -24.19237,
  "lng": 133.48853,
  "gps_when": "2015-10-20 23:35:21",
  "dist_darwin": 1332.816,
  "dist_adelaide": 1290.498
 },
 {
  "id": "9",
  "name": "HS Bochum SolarCar-Team",
  "number": 11,
  "car_name": "Sun Riser",
  "country": "de",
  "class_id": 6,
  "lat": -24.28377,
  "lng": 133.43005,
  "gps_when": "2015-10-20 23:45:18",
  "dist_darwin": 1341.47,
  "dist_adelaide": 1283.219
 },
 {
  "id": "9",
  "name": "HS Bochum SolarCar-Team",
  "number": 11,
  "car_name": "Sun Riser",
  "country": "de",
  "class_id": 6,
  "lat": -24.36404,
  "lng": 133.42699,
  "gps_when": "2015-10-20 23:55:21",
  "dist_darwin": 1350.126,
  "dist_adelaide": 1275.05
 },
 {
  "id": "9",
  "name": "HS Bochum SolarCar-Team",
  "number": 11,
  "car_name": "Sun Riser",
  "country": "de",
  "class_id": 6,
  "lat": -24.45691,
  "lng": 133.32918,
  "gps_when": "2015-10-21 00:07:11",
  "dist_darwin": 1358.201,
  "dist_adelaide": 1269.214
 },
 {
  "id": "9",
  "name": "HS Bochum SolarCar-Team",
  "number": 11,
  "car_name": "Sun Riser",
  "country": "de",
  "class_id": 6,
  "lat": -24.51215,
  "lng": 133.2563,
  "gps_when": "2015-10-21 00:15:19",
  "dist_darwin": 1362.768,
  "dist_adelaide": 1266.374
 },
 {
  "id": "9",
  "name": "HS Bochum SolarCar-Team",
  "number": 11,
  "car_name": "Sun Riser",
  "country": "de",
  "class_id": 6,
  "lat": -24.61186,
  "lng": 133.21922,
  "gps_when": "2015-10-21 00:25:19",
  "dist_darwin": 1372.925,
  "dist_adelaide": 1257.63
 },
 {
  "id": "9",
  "name": "HS Bochum SolarCar-Team",
  "number": 11,
  "car_name": "Sun Riser",
  "country": "de",
  "class_id": 6,
  "lat": -24.71741,
  "lng": 133.18019,
  "gps_when": "2015-10-21 00:35:30",
  "dist_darwin": 1383.71,
  "dist_adelaide": 1248.412
 },
 {
  "id": "9",
  "name": "HS Bochum SolarCar-Team",
  "number": 11,
  "car_name": "Sun Riser",
  "country": "de",
  "class_id": 6,
  "lat": -24.82159,
  "lng": 133.18825,
  "gps_when": "2015-10-21 00:45:18",
  "dist_darwin": 1395.238,
  "dist_adelaide": 1237.474
 },
 {
  "id": "9",
  "name": "HS Bochum SolarCar-Team",
  "number": 11,
  "car_name": "Sun Riser",
  "country": "de",
  "class_id": 6,
  "lat": -24.93097,
  "lng": 133.19614,
  "gps_when": "2015-10-21 00:55:14",
  "dist_darwin": 1407.332,
  "dist_adelaide": 1226.026
 },
 {
  "id": "9",
  "name": "HS Bochum SolarCar-Team",
  "number": 11,
  "car_name": "Sun Riser",
  "country": "de",
  "class_id": 6,
  "lat": -25.04118,
  "lng": 133.20268,
  "gps_when": "2015-10-21 01:05:17",
  "dist_darwin": 1419.493,
  "dist_adelaide": 1214.565
 },
 {
  "id": "9",
  "name": "HS Bochum SolarCar-Team",
  "number": 11,
  "car_name": "Sun Riser",
  "country": "de",
  "class_id": 6,
  "lat": -25.14981,
  "lng": 133.1944,
  "gps_when": "2015-10-21 01:15:13",
  "dist_darwin": 1431.214,
  "dist_adelaide": 1203.892
 },
 {
  "id": "9",
  "name": "HS Bochum SolarCar-Team",
  "number": 11,
  "car_name": "Sun Riser",
  "country": "de",
  "class_id": 6,
  "lat": -25.2598,
  "lng": 133.20959,
  "gps_when": "2015-10-21 01:25:13",
  "dist_darwin": 1443.512,
  "dist_adelaide": 1192.13
 },
 {
  "id": "9",
  "name": "HS Bochum SolarCar-Team",
  "number": 11,
  "car_name": "Sun Riser",
  "country": "de",
  "class_id": 6,
  "lat": -25.36752,
  "lng": 133.19202,
  "gps_when": "2015-10-21 01:35:18",
  "dist_darwin": 1454.976,
  "dist_adelaide": 1181.983
 },
 {
  "id": "9",
  "name": "HS Bochum SolarCar-Team",
  "number": 11,
  "car_name": "Sun Riser",
  "country": "de",
  "class_id": 6,
  "lat": -25.48042,
  "lng": 133.22121,
  "gps_when": "2015-10-21 01:46:05",
  "dist_darwin": 1467.842,
  "dist_adelaide": 1169.368
 },
 {
  "id": "9",
  "name": "HS Bochum SolarCar-Team",
  "number": 11,
  "car_name": "Sun Riser",
  "country": "de",
  "class_id": 6,
  "lat": -25.57391,
  "lng": 133.20911,
  "gps_when": "2015-10-21 01:55:14",
  "dist_darwin": 1477.854,
  "dist_adelaide": 1160.47
 },
 {
  "id": "9",
  "name": "HS Bochum SolarCar-Team",
  "number": 11,
  "car_name": "Sun Riser",
  "country": "de",
  "class_id": 6,
  "lat": -25.67206,
  "lng": 133.23592,
  "gps_when": "2015-10-21 02:05:13",
  "dist_darwin": 1489.062,
  "dist_adelaide": 1149.459
 },
 {
  "id": "9",
  "name": "HS Bochum SolarCar-Team",
  "number": 11,
  "car_name": "Sun Riser",
  "country": "de",
  "class_id": 6,
  "lat": -25.76683,
  "lng": 133.29164,
  "gps_when": "2015-10-21 02:16:19",
  "dist_darwin": 1500.416,
  "dist_adelaide": 1137.555
 },
 {
  "id": "9",
  "name": "HS Bochum SolarCar-Team",
  "number": 11,
  "car_name": "Sun Riser",
  "country": "de",
  "class_id": 6,
  "lat": -25.83971,
  "lng": 133.30087,
  "gps_when": "2015-10-21 02:35:12",
  "dist_darwin": 1508.549,
  "dist_adelaide": 1129.841
 },
 {
  "id": "9",
  "name": "HS Bochum SolarCar-Team",
  "number": 11,
  "car_name": "Sun Riser",
  "country": "de",
  "class_id": 6,
  "lat": -25.83968,
  "lng": 133.30087,
  "gps_when": "2015-10-21 02:45:32",
  "dist_darwin": 1508.545,
  "dist_adelaide": 1129.844
 },
 {
  "id": "9",
  "name": "HS Bochum SolarCar-Team",
  "number": 11,
  "car_name": "Sun Riser",
  "country": "de",
  "class_id": 6,
  "lat": -25.84195,
  "lng": 133.29927,
  "gps_when": "2015-10-21 02:55:23",
  "dist_darwin": 1508.765,
  "dist_adelaide": 1129.685
 },
 {
  "id": "9",
  "name": "HS Bochum SolarCar-Team",
  "number": 11,
  "car_name": "Sun Riser",
  "country": "de",
  "class_id": 6,
  "lat": -25.92012,
  "lng": 133.24828,
  "gps_when": "2015-10-21 03:05:07",
  "dist_darwin": 1516.418,
  "dist_adelaide": 1124.06
 },
 {
  "id": "9",
  "name": "HS Bochum SolarCar-Team",
  "number": 11,
  "car_name": "Sun Riser",
  "country": "de",
  "class_id": 6,
  "lat": -26.00314,
  "lng": 133.19548,
  "gps_when": "2015-10-21 03:15:07",
  "dist_darwin": 1524.603,
  "dist_adelaide": 1118.089
 },
 {
  "id": "9",
  "name": "HS Bochum SolarCar-Team",
  "number": 11,
  "car_name": "Sun Riser",
  "country": "de",
  "class_id": 6,
  "lat": -26.09865,
  "lng": 133.19949,
  "gps_when": "2015-10-21 03:25:09",
  "dist_darwin": 1535.131,
  "dist_adelaide": 1108.403
 },
 {
  "id": "9",
  "name": "HS Bochum SolarCar-Team",
  "number": 11,
  "car_name": "Sun Riser",
  "country": "de",
  "class_id": 6,
  "lat": -26.47147,
  "lng": 133.25858,
  "gps_when": "2015-10-21 04:05:19",
  "dist_darwin": 1576.959,
  "dist_adelaide": 1068.781
 },
 {
  "id": "9",
  "name": "HS Bochum SolarCar-Team",
  "number": 11,
  "car_name": "Sun Riser",
  "country": "de",
  "class_id": 6,
  "lat": -26.56512,
  "lng": 133.2506,
  "gps_when": "2015-10-21 04:15:07",
  "dist_darwin": 1587.086,
  "dist_adelaide": 1059.903
 },
 {
  "id": "9",
  "name": "HS Bochum SolarCar-Team",
  "number": 11,
  "car_name": "Sun Riser",
  "country": "de",
  "class_id": 6,
  "lat": -26.65559,
  "lng": 133.28354,
  "gps_when": "2015-10-21 04:25:06",
  "dist_darwin": 1597.545,
  "dist_adelaide": 1049.477
 },
 {
  "id": "9",
  "name": "HS Bochum SolarCar-Team",
  "number": 11,
  "car_name": "Sun Riser",
  "country": "de",
  "class_id": 6,
  "lat": -26.74588,
  "lng": 133.31989,
  "gps_when": "2015-10-21 04:35:05",
  "trailered": 0,
  "dist_darwin": 1608.042,
  "dist_adelaide": 1038.915
 },
 {
  "id": "9",
  "name": "HS Bochum SolarCar-Team",
  "number": 11,
  "car_name": "Sun Riser",
  "country": "de",
  "class_id": 6,
  "lat": -26.83983,
  "lng": 133.33855,
  "gps_when": "2015-10-21 04:45:08",
  "trailered": 0,
  "dist_darwin": 1618.644,
  "dist_adelaide": 1028.817
 },
 {
  "id": "9",
  "name": "HS Bochum SolarCar-Team",
  "number": 11,
  "car_name": "Sun Riser",
  "country": "de",
  "class_id": 6,
  "lat": -26.91982,
  "lng": 133.37535,
  "gps_when": "2015-10-21 04:55:34",
  "trailered": 0,
  "dist_darwin": 1628.023,
  "dist_adelaide": 1019.256
 },
 {
  "id": "9",
  "name": "HS Bochum SolarCar-Team",
  "number": 11,
  "car_name": "Sun Riser",
  "country": "de",
  "class_id": 6,
  "lat": -26.98923,
  "lng": 133.41353,
  "gps_when": "2015-10-21 05:05:01",
  "trailered": 0,
  "dist_darwin": 1636.27,
  "dist_adelaide": 1010.67
 },
 {
  "id": "9",
  "name": "HS Bochum SolarCar-Team",
  "number": 11,
  "car_name": "Sun Riser",
  "country": "de",
  "class_id": 6,
  "lat": -27.06807,
  "lng": 133.46002,
  "gps_when": "2015-10-21 05:15:06",
  "trailered": 0,
  "dist_darwin": 1645.696,
  "dist_adelaide": 1000.774
 },
 {
  "id": "9",
  "name": "HS Bochum SolarCar-Team",
  "number": 11,
  "car_name": "Sun Riser",
  "country": "de",
  "class_id": 6,
  "lat": -27.13663,
  "lng": 133.51743,
  "gps_when": "2015-10-21 05:25:03",
  "trailered": 0,
  "dist_darwin": 1654.195,
  "dist_adelaide": 991.382
 },
 {
  "id": "9",
  "name": "HS Bochum SolarCar-Team",
  "number": 11,
  "car_name": "Sun Riser",
  "country": "de",
  "class_id": 6,
  "lat": -27.21939,
  "lng": 133.55026,
  "gps_when": "2015-10-21 05:34:59",
  "trailered": 0,
  "dist_darwin": 1663.822,
  "dist_adelaide": 981.739
 },
 {
  "id": "9",
  "name": "HS Bochum SolarCar-Team",
  "number": 11,
  "car_name": "Sun Riser",
  "country": "de",
  "class_id": 6,
  "lat": -27.29051,
  "lng": 133.60944,
  "gps_when": "2015-10-21 05:45:02",
  "trailered": 0,
  "dist_darwin": 1672.649,
  "dist_adelaide": 972.016
 },
 {
  "id": "9",
  "name": "HS Bochum SolarCar-Team",
  "number": 11,
  "car_name": "Sun Riser",
  "country": "de",
  "class_id": 6,
  "lat": -27.36404,
  "lng": 133.66467,
  "gps_when": "2015-10-21 05:55:01",
  "trailered": 0,
  "dist_darwin": 1681.678,
  "dist_adelaide": 962.242
 },
 {
  "id": "9",
  "name": "HS Bochum SolarCar-Team",
  "number": 11,
  "car_name": "Sun Riser",
  "country": "de",
  "class_id": 6,
  "lat": -27.43671,
  "lng": 133.72083,
  "gps_when": "2015-10-21 06:05:01",
  "trailered": 0,
  "dist_darwin": 1690.641,
  "dist_adelaide": 952.512
 },
 {
  "id": "9",
  "name": "HS Bochum SolarCar-Team",
  "number": 11,
  "car_name": "Sun Riser",
  "country": "de",
  "class_id": 6,
  "lat": -27.50725,
  "lng": 133.78246,
  "gps_when": "2015-10-21 06:15:06",
  "trailered": 0,
  "dist_darwin": 1699.484,
  "dist_adelaide": 942.742
 },
 {
  "id": "9",
  "name": "HS Bochum SolarCar-Team",
  "number": 11,
  "car_name": "Sun Riser",
  "country": "de",
  "class_id": 6,
  "lat": -27.58046,
  "lng": 133.839,
  "gps_when": "2015-10-21 06:25:09",
  "trailered": 0,
  "dist_darwin": 1708.534,
  "dist_adelaide": 932.947
 },
 {
  "id": "9",
  "name": "HS Bochum SolarCar-Team",
  "number": 11,
  "car_name": "Sun Riser",
  "country": "de",
  "class_id": 6,
  "lat": -27.64981,
  "lng": 133.90927,
  "gps_when": "2015-10-21 06:35:44",
  "trailered": 0,
  "dist_darwin": 1717.438,
  "dist_adelaide": 922.905
 },
 {
  "id": "9",
  "name": "HS Bochum SolarCar-Team",
  "number": 11,
  "car_name": "Sun Riser",
  "country": "de",
  "class_id": 6,
  "lat": -27.71194,
  "lng": 133.96683,
  "gps_when": "2015-10-21 06:44:58",
  "trailered": 0,
  "dist_darwin": 1725.324,
  "dist_adelaide": 914.161
 },
 {
  "id": "9",
  "name": "HS Bochum SolarCar-Team",
  "number": 11,
  "car_name": "Sun Riser",
  "country": "de",
  "class_id": 6,
  "lat": -27.79257,
  "lng": 134.01964,
  "gps_when": "2015-10-21 06:55:43",
  "trailered": 0,
  "dist_darwin": 1735.142,
  "dist_adelaide": 903.815
 },
 {
  "id": "9",
  "name": "HS Bochum SolarCar-Team",
  "number": 11,
  "car_name": "Sun Riser",
  "country": "de",
  "class_id": 6,
  "lat": -27.87154,
  "lng": 134.03976,
  "gps_when": "2015-10-21 07:04:57",
  "trailered": 0,
  "dist_darwin": 1744.135,
  "dist_adelaide": 895.126
 },
 {
  "id": "9",
  "name": "HS Bochum SolarCar-Team",
  "number": 11,
  "car_name": "Sun Riser",
  "country": "de",
  "class_id": 6,
  "lat": -27.94804,
  "lng": 134.08981,
  "gps_when": "2015-10-21 07:14:54",
  "trailered": 0,
  "dist_darwin": 1753.455,
  "dist_adelaide": 885.314
 },
 {
  "id": "9",
  "name": "HS Bochum SolarCar-Team",
  "number": 11,
  "car_name": "Sun Riser",
  "country": "de",
  "class_id": 6,
  "lat": -28.03166,
  "lng": 134.10965,
  "gps_when": "2015-10-21 07:24:56",
  "trailered": 0,
  "dist_darwin": 1762.948,
  "dist_adelaide": 876.189
 },
 {
  "id": "9",
  "name": "HS Bochum SolarCar-Team",
  "number": 11,
  "car_name": "Sun Riser",
  "country": "de",
  "class_id": 6,
  "lat": -28.11258,
  "lng": 134.13484,
  "gps_when": "2015-10-21 07:34:56",
  "trailered": 0,
  "dist_darwin": 1772.255,
  "dist_adelaide": 867.091
 },
 {
  "id": "9",
  "name": "HS Bochum SolarCar-Team",
  "number": 11,
  "car_name": "Sun Riser",
  "country": "de",
  "class_id": 6,
  "lat": -28.11337,
  "lng": 134.1353,
  "gps_when": "2015-10-21 07:44:55",
  "trailered": 0,
  "dist_darwin": 1772.35,
  "dist_adelaide": 866.992
 },
 {
  "id": "9",
  "name": "HS Bochum SolarCar-Team",
  "number": 11,
  "car_name": "Sun Riser",
  "country": "de",
  "class_id": 6,
  "lat": -28.11336,
  "lng": 134.13531,
  "gps_when": "2015-10-21 07:54:54",
  "trailered": 0,
  "dist_darwin": 1772.349,
  "dist_adelaide": 866.993
 },
 {
  "id": "9",
  "name": "HS Bochum SolarCar-Team",
  "number": 11,
  "car_name": "Sun Riser",
  "country": "de",
  "class_id": 6,
  "lat": -28.11339,
  "lng": 134.13531,
  "gps_when": "2015-10-21 08:07:06",
  "trailered": 0,
  "dist_darwin": 1772.352,
  "dist_adelaide": 866.99
 },
 {
  "id": "9",
  "name": "HS Bochum SolarCar-Team",
  "number": 11,
  "car_name": "Sun Riser",
  "country": "de",
  "class_id": 6,
  "lat": -28.11334,
  "lng": 134.13542,
  "gps_when": "2015-10-21 08:14:53",
  "trailered": 0,
  "dist_darwin": 1772.349,
  "dist_adelaide": 866.989
 },
 {
  "id": "9",
  "name": "HS Bochum SolarCar-Team",
  "number": 11,
  "car_name": "Sun Riser",
  "country": "de",
  "class_id": 6,
  "lat": -28.11395,
  "lng": 134.1351,
  "gps_when": "2015-10-21 21:59:10",
  "trailered": 0,
  "dist_darwin": 1772.409,
  "dist_adelaide": 866.944
 },
 {
  "id": "9",
  "name": "HS Bochum SolarCar-Team",
  "number": 11,
  "car_name": "Sun Riser",
  "country": "de",
  "class_id": 6,
  "lat": -28.11395,
  "lng": 134.13513,
  "gps_when": "2015-10-21 22:08:24",
  "trailered": 0,
  "dist_darwin": 1772.409,
  "dist_adelaide": 866.943
 },
 {
  "id": "9",
  "name": "HS Bochum SolarCar-Team",
  "number": 11,
  "car_name": "Sun Riser",
  "country": "de",
  "class_id": 6,
  "lat": -28.11395,
  "lng": 134.1351,
  "gps_when": "2015-10-21 22:18:24",
  "trailered": 0,
  "dist_darwin": 1772.409,
  "dist_adelaide": 866.944
 },
 {
  "id": "9",
  "name": "HS Bochum SolarCar-Team",
  "number": 11,
  "car_name": "Sun Riser",
  "country": "de",
  "class_id": 6,
  "lat": -28.11395,
  "lng": 134.13513,
  "gps_when": "2015-10-21 22:28:23",
  "trailered": 0,
  "dist_darwin": 1772.409,
  "dist_adelaide": 866.943
 },
 {
  "id": "9",
  "name": "HS Bochum SolarCar-Team",
  "number": 11,
  "car_name": "Sun Riser",
  "country": "de",
  "class_id": 6,
  "lat": -28.1423,
  "lng": 134.13152,
  "gps_when": "2015-10-21 22:38:23",
  "trailered": 0,
  "dist_darwin": 1775.421,
  "dist_adelaide": 864.332
 },
 {
  "id": "9",
  "name": "HS Bochum SolarCar-Team",
  "number": 11,
  "car_name": "Sun Riser",
  "country": "de",
  "class_id": 6,
  "lat": -28.22769,
  "lng": 134.15321,
  "gps_when": "2015-10-21 22:48:19",
  "trailered": 0,
  "dist_darwin": 1785.144,
  "dist_adelaide": 854.97
 },
 {
  "id": "9",
  "name": "HS Bochum SolarCar-Team",
  "number": 11,
  "car_name": "Sun Riser",
  "country": "de",
  "class_id": 6,
  "lat": -28.31599,
  "lng": 134.16429,
  "gps_when": "2015-10-21 22:58:21",
  "trailered": 0,
  "dist_darwin": 1794.971,
  "dist_adelaide": 845.831
 },
 {
  "id": "9",
  "name": "HS Bochum SolarCar-Team",
  "number": 11,
  "car_name": "Sun Riser",
  "country": "de",
  "class_id": 6,
  "lat": -28.48611,
  "lng": 134.20428,
  "gps_when": "2015-10-21 23:18:20",
  "trailered": 0,
  "dist_darwin": 1814.275,
  "dist_adelaide": 827.387
 },
 {
  "id": "9",
  "name": "HS Bochum SolarCar-Team",
  "number": 11,
  "car_name": "Sun Riser",
  "country": "de",
  "class_id": 6,
  "lat": -28.55821,
  "lng": 134.25969,
  "gps_when": "2015-10-21 23:28:20",
  "trailered": 0,
  "dist_darwin": 1823.225,
  "dist_adelaide": 817.756
 },
 {
  "id": "9",
  "name": "HS Bochum SolarCar-Team",
  "number": 11,
  "car_name": "Sun Riser",
  "country": "de",
  "class_id": 6,
  "lat": -28.62682,
  "lng": 134.3197,
  "gps_when": "2015-10-21 23:38:17",
  "trailered": 0,
  "dist_darwin": 1831.897,
  "dist_adelaide": 808.25
 },
 {
  "id": "9",
  "name": "HS Bochum SolarCar-Team",
  "number": 11,
  "car_name": "Sun Riser",
  "country": "de",
  "class_id": 6,
  "lat": -28.66722,
  "lng": 134.40738,
  "gps_when": "2015-10-21 23:48:16",
  "trailered": 0,
  "dist_darwin": 1838.09,
  "dist_adelaide": 800.199
 },
 {
  "id": "9",
  "name": "HS Bochum SolarCar-Team",
  "number": 11,
  "car_name": "Sun Riser",
  "country": "de",
  "class_id": 6,
  "lat": -28.72691,
  "lng": 134.47697,
  "gps_when": "2015-10-21 23:58:16",
  "trailered": 0,
  "dist_darwin": 1846.025,
  "dist_adelaide": 791.132
 },
 {
  "id": "9",
  "name": "HS Bochum SolarCar-Team",
  "number": 11,
  "car_name": "Sun Riser",
  "country": "de",
  "class_id": 6,
  "lat": -28.79967,
  "lng": 134.53357,
  "gps_when": "2015-10-22 00:08:15",
  "trailered": 0,
  "dist_darwin": 1855.117,
  "dist_adelaide": 781.397
 },
 {
  "id": "9",
  "name": "HS Bochum SolarCar-Team",
  "number": 11,
  "car_name": "Sun Riser",
  "country": "de",
  "class_id": 6,
  "lat": -28.85881,
  "lng": 134.60483,
  "gps_when": "2015-10-22 00:18:14",
  "trailered": 0,
  "dist_darwin": 1863.056,
  "dist_adelaide": 772.322
 },
 {
  "id": "9",
  "name": "HS Bochum SolarCar-Team",
  "number": 11,
  "car_name": "Sun Riser",
  "country": "de",
  "class_id": 6,
  "lat": -28.92975,
  "lng": 134.66382,
  "gps_when": "2015-10-22 00:28:14",
  "trailered": 0,
  "dist_darwin": 1872.022,
  "dist_adelaide": 762.664
 },
 {
  "id": "9",
  "name": "HS Bochum SolarCar-Team",
  "number": 11,
  "car_name": "Sun Riser",
  "country": "de",
  "class_id": 6,
  "lat": -29.00706,
  "lng": 134.70848,
  "gps_when": "2015-10-22 00:38:40",
  "trailered": 0,
  "dist_darwin": 1881.37,
  "dist_adelaide": 753.041
 },
 {
  "id": "9",
  "name": "HS Bochum SolarCar-Team",
  "number": 11,
  "car_name": "Sun Riser",
  "country": "de",
  "class_id": 6,
  "lat": -29.01825,
  "lng": 134.75441,
  "gps_when": "2015-10-22 00:48:13",
  "trailered": 0,
  "dist_darwin": 1883.596,
  "dist_adelaide": 749.844
 },
 {
  "id": "9",
  "name": "HS Bochum SolarCar-Team",
  "number": 11,
  "car_name": "Sun Riser",
  "country": "de",
  "class_id": 6,
  "lat": -29.01823,
  "lng": 134.75439,
  "gps_when": "2015-10-22 00:58:18",
  "trailered": 0,
  "dist_darwin": 1883.593,
  "dist_adelaide": 749.847
 },
 {
  "id": "9",
  "name": "HS Bochum SolarCar-Team",
  "number": 11,
  "car_name": "Sun Riser",
  "country": "de",
  "class_id": 6,
  "lat": -29.01826,
  "lng": 134.75435,
  "gps_when": "2015-10-22 01:08:12",
  "trailered": 0,
  "dist_darwin": 1883.595,
  "dist_adelaide": 749.845
 },
 {
  "id": "9",
  "name": "HS Bochum SolarCar-Team",
  "number": 11,
  "car_name": "Sun Riser",
  "country": "de",
  "class_id": 6,
  "lat": -29.02544,
  "lng": 134.77284,
  "gps_when": "2015-10-22 01:18:59",
  "trailered": 0,
  "dist_darwin": 1884.783,
  "dist_adelaide": 748.299
 },
 {
  "id": "9",
  "name": "HS Bochum SolarCar-Team",
  "number": 11,
  "car_name": "Sun Riser",
  "country": "de",
  "class_id": 6,
  "lat": -29.07858,
  "lng": 134.8573,
  "gps_when": "2015-10-22 01:28:10",
  "trailered": 0,
  "dist_darwin": 1892.427,
  "dist_adelaide": 739.257
 },
 {
  "id": "9",
  "name": "HS Bochum SolarCar-Team",
  "number": 11,
  "car_name": "Sun Riser",
  "country": "de",
  "class_id": 6,
  "lat": -29.14983,
  "lng": 134.92241,
  "gps_when": "2015-10-22 01:38:10",
  "trailered": 0,
  "dist_darwin": 1901.607,
  "dist_adelaide": 729.315
 },
 {
  "id": "9",
  "name": "HS Bochum SolarCar-Team",
  "number": 11,
  "car_name": "Sun Riser",
  "country": "de",
  "class_id": 6,
  "lat": -29.22958,
  "lng": 134.95811,
  "gps_when": "2015-10-22 01:48:12",
  "trailered": 0,
  "dist_darwin": 1911.037,
  "dist_adelaide": 719.855
 },
 {
  "id": "9",
  "name": "HS Bochum SolarCar-Team",
  "number": 11,
  "car_name": "Sun Riser",
  "country": "de",
  "class_id": 6,
  "lat": -29.31685,
  "lng": 134.97603,
  "gps_when": "2015-10-22 01:58:09",
  "trailered": 0,
  "dist_darwin": 1920.869,
  "dist_adelaide": 710.46
 },
 {
  "id": "9",
  "name": "HS Bochum SolarCar-Team",
  "number": 11,
  "car_name": "Sun Riser",
  "country": "de",
  "class_id": 6,
  "lat": -29.40152,
  "lng": 135.004,
  "gps_when": "2015-10-22 02:08:08",
  "trailered": 0,
  "dist_darwin": 1930.652,
  "dist_adelaide": 700.876
 },
 {
  "id": "9",
  "name": "HS Bochum SolarCar-Team",
  "number": 11,
  "car_name": "Sun Riser",
  "country": "de",
  "class_id": 6,
  "lat": -29.48763,
  "lng": 135.02356,
  "gps_when": "2015-10-22 02:18:11",
  "trailered": 0,
  "dist_darwin": 1940.396,
  "dist_adelaide": 691.543
 },
 {
  "id": "9",
  "name": "HS Bochum SolarCar-Team",
  "number": 11,
  "car_name": "Sun Riser",
  "country": "de",
  "class_id": 6,
  "lat": -29.56531,
  "lng": 135.06915,
  "gps_when": "2015-10-22 02:28:16",
  "trailered": 0,
  "dist_darwin": 1949.829,
  "dist_adelaide": 681.853
 },
 {
  "id": "9",
  "name": "HS Bochum SolarCar-Team",
  "number": 11,
  "car_name": "Sun Riser",
  "country": "de",
  "class_id": 6,
  "lat": -29.62964,
  "lng": 135.13327,
  "gps_when": "2015-10-22 02:38:07",
  "trailered": 0,
  "dist_darwin": 1958.256,
  "dist_adelaide": 672.627
 },
 {
  "id": "9",
  "name": "HS Bochum SolarCar-Team",
  "number": 11,
  "car_name": "Sun Riser",
  "country": "de",
  "class_id": 6,
  "lat": -29.71764,
  "lng": 135.12682,
  "gps_when": "2015-10-22 02:48:10",
  "trailered": 0,
  "dist_darwin": 1967.597,
  "dist_adelaide": 664.313
 },
 {
  "id": "9",
  "name": "HS Bochum SolarCar-Team",
  "number": 11,
  "car_name": "Sun Riser",
  "country": "de",
  "class_id": 6,
  "lat": -29.80515,
  "lng": 135.12173,
  "gps_when": "2015-10-22 02:58:06",
  "trailered": 0,
  "dist_darwin": 1976.922,
  "dist_adelaide": 656.024
 },
 {
  "id": "9",
  "name": "HS Bochum SolarCar-Team",
  "number": 11,
  "car_name": "Sun Riser",
  "country": "de",
  "class_id": 6,
  "lat": -29.88988,
  "lng": 135.13879,
  "gps_when": "2015-10-22 03:08:05",
  "trailered": 0,
  "dist_darwin": 1986.457,
  "dist_adelaide": 646.999
 },
 {
  "id": "9",
  "name": "HS Bochum SolarCar-Team",
  "number": 11,
  "car_name": "Sun Riser",
  "country": "de",
  "class_id": 6,
  "lat": -29.97589,
  "lng": 135.17065,
  "gps_when": "2015-10-22 03:18:05",
  "trailered": 0,
  "dist_darwin": 1996.471,
  "dist_adelaide": 637.165
 },
 {
  "id": "9",
  "name": "HS Bochum SolarCar-Team",
  "number": 11,
  "car_name": "Sun Riser",
  "country": "de",
  "class_id": 6,
  "lat": -30.08401,
  "lng": 135.19524,
  "gps_when": "2015-10-22 03:29:49",
  "trailered": 0,
  "dist_darwin": 2008.702,
  "dist_adelaide": 625.552
 },
 {
  "id": "9",
  "name": "HS Bochum SolarCar-Team",
  "number": 11,
  "car_name": "Sun Riser",
  "country": "de",
  "class_id": 6,
  "lat": -30.23886,
  "lng": 135.25777,
  "gps_when": "2015-10-22 03:48:06",
  "trailered": 0,
  "dist_darwin": 2026.847,
  "dist_adelaide": 607.646
 },
 {
  "id": "9",
  "name": "HS Bochum SolarCar-Team",
  "number": 11,
  "car_name": "Sun Riser",
  "country": "de",
  "class_id": 6,
  "lat": -30.32576,
  "lng": 135.3017,
  "gps_when": "2015-10-22 03:58:06",
  "trailered": 0,
  "dist_darwin": 2037.235,
  "dist_adelaide": 597.18
 },
 {
  "id": "9",
  "name": "HS Bochum SolarCar-Team",
  "number": 11,
  "car_name": "Sun Riser",
  "country": "de",
  "class_id": 6,
  "lat": -30.40988,
  "lng": 135.34894,
  "gps_when": "2015-10-22 04:08:02",
  "trailered": 0,
  "dist_darwin": 2047.4,
  "dist_adelaide": 586.825
 },
 {
  "id": "9",
  "name": "HS Bochum SolarCar-Team",
  "number": 11,
  "car_name": "Sun Riser",
  "country": "de",
  "class_id": 6,
  "lat": -30.5052,
  "lng": 135.34561,
  "gps_when": "2015-10-22 04:18:04",
  "trailered": 0,
  "dist_darwin": 2057.6,
  "dist_adelaide": 577.879
 },
 {
  "id": "9",
  "name": "HS Bochum SolarCar-Team",
  "number": 11,
  "car_name": "Sun Riser",
  "country": "de",
  "class_id": 6,
  "lat": -30.59412,
  "lng": 135.38335,
  "gps_when": "2015-10-22 04:28:04",
  "trailered": 0,
  "dist_darwin": 2068.061,
  "dist_adelaide": 567.552
 },
 {
  "id": "9",
  "name": "HS Bochum SolarCar-Team",
  "number": 11,
  "car_name": "Sun Riser",
  "country": "de",
  "class_id": 6,
  "lat": -30.67862,
  "lng": 135.44182,
  "gps_when": "2015-10-22 04:38:24",
  "trailered": 0,
  "dist_darwin": 2078.528,
  "dist_adelaide": 556.624
 },
 {
  "id": "9",
  "name": "HS Bochum SolarCar-Team",
  "number": 11,
  "car_name": "Sun Riser",
  "country": "de",
  "class_id": 6,
  "lat": -30.75266,
  "lng": 135.50456,
  "gps_when": "2015-10-22 04:48:03",
  "trailered": 0,
  "dist_darwin": 2087.975,
  "dist_adelaide": 546.482
 },
 {
  "id": "9",
  "name": "HS Bochum SolarCar-Team",
  "number": 11,
  "car_name": "Sun Riser",
  "country": "de",
  "class_id": 6,
  "lat": -30.8403,
  "lng": 135.56866,
  "gps_when": "2015-10-22 04:58:50",
  "trailered": 0,
  "dist_darwin": 2098.924,
  "dist_adelaide": 534.983
 },
 {
  "id": "9",
  "name": "HS Bochum SolarCar-Team",
  "number": 11,
  "car_name": "Sun Riser",
  "country": "de",
  "class_id": 6,
  "lat": -30.88164,
  "lng": 135.65887,
  "gps_when": "2015-10-22 05:08:02",
  "trailered": 0,
  "dist_darwin": 2105.527,
  "dist_adelaide": 526.62
 },
 {
  "id": "9",
  "name": "HS Bochum SolarCar-Team",
  "number": 11,
  "car_name": "Sun Riser",
  "country": "de",
  "class_id": 6,
  "lat": -30.95103,
  "lng": 135.73752,
  "gps_when": "2015-10-22 05:18:01",
  "trailered": 0,
  "dist_darwin": 2114.89,
  "dist_adelaide": 516.168
 },
 {
  "id": "9",
  "name": "HS Bochum SolarCar-Team",
  "number": 11,
  "car_name": "Sun Riser",
  "country": "de",
  "class_id": 6,
  "lat": -30.96976,
  "lng": 135.75078,
  "gps_when": "2015-10-22 05:28:00",
  "trailered": 0,
  "dist_darwin": 2117.225,
  "dist_adelaide": 513.734
 },
 {
  "id": "9",
  "name": "HS Bochum SolarCar-Team",
  "number": 11,
  "car_name": "Sun Riser",
  "country": "de",
  "class_id": 6,
  "lat": -30.96983,
  "lng": 135.75072,
  "gps_when": "2015-10-22 05:38:00",
  "trailered": 0,
  "dist_darwin": 2117.231,
  "dist_adelaide": 513.73
 },
 {
  "id": "9",
  "name": "HS Bochum SolarCar-Team",
  "number": 11,
  "car_name": "Sun Riser",
  "country": "de",
  "class_id": 6,
  "lat": -30.96983,
  "lng": 135.7507,
  "gps_when": "2015-10-22 05:48:06",
  "trailered": 0,
  "dist_darwin": 2117.231,
  "dist_adelaide": 513.731
 },
 {
  "id": "9",
  "name": "HS Bochum SolarCar-Team",
  "number": 11,
  "car_name": "Sun Riser",
  "country": "de",
  "class_id": 6,
  "lat": -31.01375,
  "lng": 135.78531,
  "gps_when": "2015-10-22 05:58:20",
  "trailered": 0,
  "dist_darwin": 2122.793,
  "dist_adelaide": 507.853
 },
 {
  "id": "9",
  "name": "HS Bochum SolarCar-Team",
  "number": 11,
  "car_name": "Sun Riser",
  "country": "de",
  "class_id": 6,
  "lat": -31.08472,
  "lng": 135.86438,
  "gps_when": "2015-10-22 06:08:49",
  "trailered": 0,
  "dist_darwin": 2132.358,
  "dist_adelaide": 497.246
 },
 {
  "id": "9",
  "name": "HS Bochum SolarCar-Team",
  "number": 11,
  "car_name": "Sun Riser",
  "country": "de",
  "class_id": 6,
  "lat": -31.1602,
  "lng": 136.05597,
  "gps_when": "2015-10-22 06:27:57",
  "trailered": 0,
  "dist_darwin": 2145.263,
  "dist_adelaide": 480.963
 },
 {
  "id": "9",
  "name": "HS Bochum SolarCar-Team",
  "number": 11,
  "car_name": "Sun Riser",
  "country": "de",
  "class_id": 6,
  "lat": -31.17863,
  "lng": 136.16592,
  "gps_when": "2015-10-22 06:37:57",
  "trailered": 0,
  "dist_darwin": 2150.067,
  "dist_adelaide": 474.184
 },
 {
  "id": "9",
  "name": "HS Bochum SolarCar-Team",
  "number": 11,
  "car_name": "Sun Riser",
  "country": "de",
  "class_id": 6,
  "lat": -31.19415,
  "lng": 136.27527,
  "gps_when": "2015-10-22 06:47:56",
  "trailered": 0,
  "dist_darwin": 2154.593,
  "dist_adelaide": 467.856
 },
 {
  "id": "9",
  "name": "HS Bochum SolarCar-Team",
  "number": 11,
  "car_name": "Sun Riser",
  "country": "de",
  "class_id": 6,
  "lat": -31.23466,
  "lng": 136.37465,
  "gps_when": "2015-10-22 06:57:56",
  "trailered": 0,
  "dist_darwin": 2161.564,
  "dist_adelaide": 459.597
 },
 {
  "id": "9",
  "name": "HS Bochum SolarCar-Team",
  "number": 11,
  "car_name": "Sun Riser",
  "country": "de",
  "class_id": 6,
  "lat": -31.23149,
  "lng": 136.43796,
  "gps_when": "2015-10-22 07:07:55",
  "trailered": 0,
  "dist_darwin": 2162.936,
  "dist_adelaide": 457.283
 },
 {
  "id": "9",
  "name": "HS Bochum SolarCar-Team",
  "number": 11,
  "car_name": "Sun Riser",
  "country": "de",
  "class_id": 6,
  "lat": -31.24864,
  "lng": 136.54924,
  "gps_when": "2015-10-22 07:17:55",
  "trailered": 0,
  "dist_darwin": 2167.808,
  "dist_adelaide": 451.075
 },
 {
  "id": "9",
  "name": "HS Bochum SolarCar-Team",
  "number": 11,
  "car_name": "Sun Riser",
  "country": "de",
  "class_id": 6,
  "lat": -31.26447,
  "lng": 136.66814,
  "gps_when": "2015-10-22 07:27:54",
  "trailered": 0,
  "dist_darwin": 2172.804,
  "dist_adelaide": 444.878
 },
 {
  "id": "9",
  "name": "HS Bochum SolarCar-Team",
  "number": 11,
  "car_name": "Sun Riser",
  "country": "de",
  "class_id": 6,
  "lat": -31.24867,
  "lng": 136.77406,
  "gps_when": "2015-10-22 07:38:39",
  "trailered": 0,
  "dist_darwin": 2174.135,
  "dist_adelaide": 442.601
 },
 {
  "id": "9",
  "name": "HS Bochum SolarCar-Team",
  "number": 11,
  "car_name": "Sun Riser",
  "country": "de",
  "class_id": 6,
  "lat": -31.2487,
  "lng": 136.77383,
  "gps_when": "2015-10-22 21:11:11",
  "trailered": 0,
  "dist_darwin": 2174.131,
  "dist_adelaide": 442.606
 },
 {
  "id": "9",
  "name": "HS Bochum SolarCar-Team",
  "number": 11,
  "car_name": "Sun Riser",
  "country": "de",
  "class_id": 6,
  "lat": -31.2487,
  "lng": 136.77388,
  "gps_when": "2015-10-22 21:20:34",
  "trailered": 0,
  "dist_darwin": 2174.133,
  "dist_adelaide": 442.604
 },
 {
  "id": "9",
  "name": "HS Bochum SolarCar-Team",
  "number": 11,
  "car_name": "Sun Riser",
  "country": "de",
  "class_id": 6,
  "lat": -31.24867,
  "lng": 136.77391,
  "gps_when": "2015-10-22 21:30:34",
  "trailered": 0,
  "dist_darwin": 2174.131,
  "dist_adelaide": 442.606
 },
 {
  "id": "9",
  "name": "HS Bochum SolarCar-Team",
  "number": 11,
  "car_name": "Sun Riser",
  "country": "de",
  "class_id": 6,
  "lat": -31.24869,
  "lng": 136.77388,
  "gps_when": "2015-10-22 21:40:33",
  "trailered": 0,
  "dist_darwin": 2174.132,
  "dist_adelaide": 442.605
 },
 {
  "id": "9",
  "name": "HS Bochum SolarCar-Team",
  "number": 11,
  "car_name": "Sun Riser",
  "country": "de",
  "class_id": 6,
  "lat": -31.2487,
  "lng": 136.77388,
  "gps_when": "2015-10-22 21:50:35",
  "trailered": 0,
  "dist_darwin": 2174.133,
  "dist_adelaide": 442.604
 },
 {
  "id": "9",
  "name": "HS Bochum SolarCar-Team",
  "number": 11,
  "car_name": "Sun Riser",
  "country": "de",
  "class_id": 6,
  "lat": -31.2487,
  "lng": 136.77388,
  "gps_when": "2015-10-22 22:00:32",
  "trailered": 0,
  "dist_darwin": 2174.133,
  "dist_adelaide": 442.604
 },
 {
  "id": "9",
  "name": "HS Bochum SolarCar-Team",
  "number": 11,
  "car_name": "Sun Riser",
  "country": "de",
  "class_id": 6,
  "lat": -31.24872,
  "lng": 136.77388,
  "gps_when": "2015-10-22 22:10:35",
  "trailered": 0,
  "dist_darwin": 2174.135,
  "dist_adelaide": 442.602
 },
 {
  "id": "9",
  "name": "HS Bochum SolarCar-Team",
  "number": 11,
  "car_name": "Sun Riser",
  "country": "de",
  "class_id": 6,
  "lat": -31.2487,
  "lng": 136.77391,
  "gps_when": "2015-10-22 22:20:31",
  "trailered": 0,
  "dist_darwin": 2174.134,
  "dist_adelaide": 442.603
 },
 {
  "id": "9",
  "name": "HS Bochum SolarCar-Team",
  "number": 11,
  "car_name": "Sun Riser",
  "country": "de",
  "class_id": 6,
  "lat": -31.24869,
  "lng": 136.7738,
  "gps_when": "2015-10-22 22:30:33",
  "trailered": 0,
  "dist_darwin": 2174.13,
  "dist_adelaide": 442.608
 },
 {
  "id": "9",
  "name": "HS Bochum SolarCar-Team",
  "number": 11,
  "car_name": "Sun Riser",
  "country": "de",
  "class_id": 6,
  "lat": -31.26389,
  "lng": 136.81042,
  "gps_when": "2015-10-22 22:40:33",
  "trailered": 0,
  "dist_darwin": 2176.79,
  "dist_adelaide": 439.739
 },
 {
  "id": "9",
  "name": "HS Bochum SolarCar-Team",
  "number": 11,
  "car_name": "Sun Riser",
  "country": "de",
  "class_id": 6,
  "lat": -31.34274,
  "lng": 136.87534,
  "gps_when": "2015-10-22 22:50:32",
  "trailered": 0,
  "dist_darwin": 2187.011,
  "dist_adelaide": 429.318
 },
 {
  "id": "9",
  "name": "HS Bochum SolarCar-Team",
  "number": 11,
  "car_name": "Sun Riser",
  "country": "de",
  "class_id": 6,
  "lat": -31.39754,
  "lng": 136.96622,
  "gps_when": "2015-10-22 23:00:29",
  "trailered": 0,
  "dist_darwin": 2195.449,
  "dist_adelaide": 420.524
 },
 {
  "id": "9",
  "name": "HS Bochum SolarCar-Team",
  "number": 11,
  "car_name": "Sun Riser",
  "country": "de",
  "class_id": 6,
  "lat": -31.45901,
  "lng": 137.03798,
  "gps_when": "2015-10-22 23:10:28",
  "trailered": 0,
  "dist_darwin": 2204.05,
  "dist_adelaide": 411.739
 },
 {
  "id": "9",
  "name": "HS Bochum SolarCar-Team",
  "number": 11,
  "car_name": "Sun Riser",
  "country": "de",
  "class_id": 6,
  "lat": -31.52136,
  "lng": 137.11774,
  "gps_when": "2015-10-22 23:20:43",
  "trailered": 0,
  "dist_darwin": 2212.99,
  "dist_adelaide": 402.643
 },
 {
  "id": "9",
  "name": "HS Bochum SolarCar-Team",
  "number": 11,
  "car_name": "Sun Riser",
  "country": "de",
  "class_id": 6,
  "lat": -31.61174,
  "lng": 137.1445,
  "gps_when": "2015-10-22 23:31:00",
  "trailered": 0,
  "dist_darwin": 2223.322,
  "dist_adelaide": 392.335
 },
 {
  "id": "9",
  "name": "HS Bochum SolarCar-Team",
  "number": 11,
  "car_name": "Sun Riser",
  "country": "de",
  "class_id": 6,
  "lat": -31.69781,
  "lng": 137.20958,
  "gps_when": "2015-10-22 23:43:02",
  "trailered": 0,
  "dist_darwin": 2234.335,
  "dist_adelaide": 381.257
 },
 {
  "id": "9",
  "name": "HS Bochum SolarCar-Team",
  "number": 11,
  "car_name": "Sun Riser",
  "country": "de",
  "class_id": 6,
  "lat": -31.7489,
  "lng": 137.26022,
  "gps_when": "2015-10-22 23:50:29",
  "trailered": 0,
  "dist_darwin": 2241.233,
  "dist_adelaide": 374.316
 },
 {
  "id": "9",
  "name": "HS Bochum SolarCar-Team",
  "number": 11,
  "car_name": "Sun Riser",
  "country": "de",
  "class_id": 6,
  "lat": -31.82492,
  "lng": 137.32005,
  "gps_when": "2015-10-23 00:00:28",
  "trailered": 0,
  "dist_darwin": 2251.038,
  "dist_adelaide": 364.492
 },
 {
  "id": "9",
  "name": "HS Bochum SolarCar-Team",
  "number": 11,
  "car_name": "Sun Riser",
  "country": "de",
  "class_id": 6,
  "lat": -31.90829,
  "lng": 137.36714,
  "gps_when": "2015-10-23 00:10:25",
  "trailered": 0,
  "dist_darwin": 2261.235,
  "dist_adelaide": 354.293
 },
 {
  "id": "9",
  "name": "HS Bochum SolarCar-Team",
  "number": 11,
  "car_name": "Sun Riser",
  "country": "de",
  "class_id": 6,
  "lat": -31.99077,
  "lng": 137.41699,
  "gps_when": "2015-10-23 00:20:27",
  "trailered": 0,
  "dist_darwin": 2271.422,
  "dist_adelaide": 344.111
 },
 {
  "id": "9",
  "name": "HS Bochum SolarCar-Team",
  "number": 11,
  "car_name": "Sun Riser",
  "country": "de",
  "class_id": 6,
  "lat": -32.07727,
  "lng": 137.44389,
  "gps_when": "2015-10-23 00:30:24",
  "trailered": 0,
  "dist_darwin": 2281.339,
  "dist_adelaide": 334.191
 },
 {
  "id": "9",
  "name": "HS Bochum SolarCar-Team",
  "number": 11,
  "car_name": "Sun Riser",
  "country": "de",
  "class_id": 6,
  "lat": -32.16208,
  "lng": 137.46906,
  "gps_when": "2015-10-23 00:40:23",
  "trailered": 0,
  "dist_darwin": 2291.025,
  "dist_adelaide": 324.502
 },
 {
  "id": "9",
  "name": "HS Bochum SolarCar-Team",
  "number": 11,
  "car_name": "Sun Riser",
  "country": "de",
  "class_id": 6,
  "lat": -32.23796,
  "lng": 137.54185,
  "gps_when": "2015-10-23 00:50:35",
  "trailered": 0,
  "dist_darwin": 2301.208,
  "dist_adelaide": 314.348
 },
 {
  "id": "9",
  "name": "HS Bochum SolarCar-Team",
  "number": 11,
  "car_name": "Sun Riser",
  "country": "de",
  "class_id": 6,
  "lat": -32.32166,
  "lng": 137.59073,
  "gps_when": "2015-10-23 01:00:25",
  "trailered": 0,
  "dist_darwin": 2311.493,
  "dist_adelaide": 304.088
 },
 {
  "id": "9",
  "name": "HS Bochum SolarCar-Team",
  "number": 11,
  "car_name": "Sun Riser",
  "country": "de",
  "class_id": 6,
  "lat": -32.40015,
  "lng": 137.65346,
  "gps_when": "2015-10-23 01:10:28",
  "trailered": 0,
  "dist_darwin": 2321.652,
  "dist_adelaide": 294.002
 },
 {
  "id": "9",
  "name": "HS Bochum SolarCar-Team",
  "number": 11,
  "car_name": "Sun Riser",
  "country": "de",
  "class_id": 6,
  "lat": -32.46251,
  "lng": 137.73576,
  "gps_when": "2015-10-23 01:20:25",
  "trailered": 0,
  "dist_darwin": 2330.72,
  "dist_adelaide": 285.151
 },
 {
  "id": "9",
  "name": "HS Bochum SolarCar-Team",
  "number": 11,
  "car_name": "Sun Riser",
  "country": "de",
  "class_id": 6,
  "lat": -32.50874,
  "lng": 137.79477,
  "gps_when": "2015-10-23 01:30:30",
  "trailered": 0,
  "dist_darwin": 2337.388,
  "dist_adelaide": 278.704
 },
 {
  "id": "9",
  "name": "HS Bochum SolarCar-Team",
  "number": 11,
  "car_name": "Sun Riser",
  "country": "de",
  "class_id": 6,
  "lat": -32.509,
  "lng": 137.79713,
  "gps_when": "2015-10-23 01:40:56",
  "trailered": 0,
  "dist_darwin": 2337.488,
  "dist_adelaide": 278.618
 },
 {
  "id": "9",
  "name": "HS Bochum SolarCar-Team",
  "number": 11,
  "car_name": "Sun Riser",
  "country": "de",
  "class_id": 6,
  "lat": -32.509,
  "lng": 137.79716,
  "gps_when": "2015-10-23 01:50:59",
  "trailered": 0,
  "dist_darwin": 2337.489,
  "dist_adelaide": 278.617
 },
 {
  "id": "9",
  "name": "HS Bochum SolarCar-Team",
  "number": 11,
  "car_name": "Sun Riser",
  "country": "de",
  "class_id": 6,
  "lat": -32.56325,
  "lng": 137.87077,
  "gps_when": "2015-10-23 02:10:37",
  "trailered": 0,
  "dist_darwin": 2345.458,
  "dist_adelaide": 271.025
 },
 {
  "id": "9",
  "name": "HS Bochum SolarCar-Team",
  "number": 11,
  "car_name": "Sun Riser",
  "country": "de",
  "class_id": 6,
  "lat": -32.65425,
  "lng": 137.92706,
  "gps_when": "2015-10-23 02:20:30",
  "trailered": 0,
  "dist_darwin": 2356.747,
  "dist_adelaide": 259.937
 },
 {
  "id": "9",
  "name": "HS Bochum SolarCar-Team",
  "number": 11,
  "car_name": "Sun Riser",
  "country": "de",
  "class_id": 6,
  "lat": -32.75861,
  "lng": 137.9505,
  "gps_when": "2015-10-23 02:30:17",
  "trailered": 0,
  "dist_darwin": 2368.412,
  "dist_adelaide": 248.153
 },
 {
  "id": "9",
  "name": "HS Bochum SolarCar-Team",
  "number": 11,
  "car_name": "Sun Riser",
  "country": "de",
  "class_id": 6,
  "lat": -32.86095,
  "lng": 137.98227,
  "gps_when": "2015-10-23 02:40:23",
  "trailered": 0,
  "dist_darwin": 2380.123,
  "dist_adelaide": 236.401
 },
 {
  "id": "9",
  "name": "HS Bochum SolarCar-Team",
  "number": 11,
  "car_name": "Sun Riser",
  "country": "de",
  "class_id": 6,
  "lat": -32.96431,
  "lng": 137.98257,
  "gps_when": "2015-10-23 02:50:16",
  "trailered": 0,
  "dist_darwin": 2390.968,
  "dist_adelaide": 225.262
 },
 {
  "id": "9",
  "name": "HS Bochum SolarCar-Team",
  "number": 11,
  "car_name": "Sun Riser",
  "country": "de",
  "class_id": 6,
  "lat": -33.04858,
  "lng": 138.03307,
  "gps_when": "2015-10-23 03:00:19",
  "trailered": 0,
  "dist_darwin": 2401.362,
  "dist_adelaide": 215.025
 },
 {
  "id": "9",
  "name": "HS Bochum SolarCar-Team",
  "number": 11,
  "car_name": "Sun Riser",
  "country": "de",
  "class_id": 6,
  "lat": -33.14011,
  "lng": 138.06845,
  "gps_when": "2015-10-23 03:10:18",
  "trailered": 0,
  "dist_darwin": 2412.05,
  "dist_adelaide": 204.36
 },
 {
  "id": "9",
  "name": "HS Bochum SolarCar-Team",
  "number": 11,
  "car_name": "Sun Riser",
  "country": "de",
  "class_id": 6,
  "lat": -33.22246,
  "lng": 138.10643,
  "gps_when": "2015-10-23 03:20:30",
  "trailered": 0,
  "dist_darwin": 2421.854,
  "dist_adelaide": 194.633
 },
 {
  "id": "9",
  "name": "HS Bochum SolarCar-Team",
  "number": 11,
  "car_name": "Sun Riser",
  "country": "de",
  "class_id": 6,
  "lat": -33.29916,
  "lng": 138.17023,
  "gps_when": "2015-10-23 03:30:38",
  "trailered": 0,
  "dist_darwin": 2431.866,
  "dist_adelaide": 184.998
 },
 {
  "id": "9",
  "name": "HS Bochum SolarCar-Team",
  "number": 11,
  "car_name": "Sun Riser",
  "country": "de",
  "class_id": 6,
  "lat": -33.38597,
  "lng": 138.17168,
  "gps_when": "2015-10-23 03:40:14",
  "trailered": 0,
  "dist_darwin": 2441.005,
  "dist_adelaide": 175.558
 },
 {
  "id": "9",
  "name": "HS Bochum SolarCar-Team",
  "number": 11,
  "car_name": "Sun Riser",
  "country": "de",
  "class_id": 6,
  "lat": -33.48155,
  "lng": 138.17226,
  "gps_when": "2015-10-23 03:50:16",
  "trailered": 0,
  "dist_darwin": 2451.039,
  "dist_adelaide": 165.215
 },
 {
  "id": "9",
  "name": "HS Bochum SolarCar-Team",
  "number": 11,
  "car_name": "Sun Riser",
  "country": "de",
  "class_id": 6,
  "lat": -33.56734,
  "lng": 138.2247,
  "gps_when": "2015-10-23 04:00:16",
  "trailered": 0,
  "dist_darwin": 2461.645,
  "dist_adelaide": 154.816
 },
 {
  "id": "9",
  "name": "HS Bochum SolarCar-Team",
  "number": 11,
  "car_name": "Sun Riser",
  "country": "de",
  "class_id": 6,
  "lat": -33.67255,
  "lng": 138.22067,
  "gps_when": "2015-10-23 04:10:15",
  "trailered": 0,
  "dist_darwin": 2472.549,
  "dist_adelaide": 143.537
 },
 {
  "id": "9",
  "name": "HS Bochum SolarCar-Team",
  "number": 11,
  "car_name": "Sun Riser",
  "country": "de",
  "class_id": 6,
  "lat": -33.78197,
  "lng": 138.20773,
  "gps_when": "2015-10-23 04:20:11",
  "trailered": 0,
  "dist_darwin": 2483.631,
  "dist_adelaide": 132.104
 },
 {
  "id": "9",
  "name": "HS Bochum SolarCar-Team",
  "number": 11,
  "car_name": "Sun Riser",
  "country": "de",
  "class_id": 6,
  "lat": -33.88519,
  "lng": 138.17374,
  "gps_when": "2015-10-23 04:30:11",
  "trailered": 0,
  "dist_darwin": 2493.439,
  "dist_adelaide": 122.09
 },
 {
  "id": "9",
  "name": "HS Bochum SolarCar-Team",
  "number": 11,
  "car_name": "Sun Riser",
  "country": "de",
  "class_id": 6,
  "lat": -33.96994,
  "lng": 138.18956,
  "gps_when": "2015-10-23 04:40:13",
  "trailered": 0,
  "dist_darwin": 2502.817,
  "dist_adelaide": 112.718
 },
 {
  "id": "9",
  "name": "HS Bochum SolarCar-Team",
  "number": 11,
  "car_name": "Sun Riser",
  "country": "de",
  "class_id": 6,
  "lat": -34.03865,
  "lng": 138.20901,
  "gps_when": "2015-10-23 04:50:13",
  "trailered": 0,
  "dist_darwin": 2510.619,
  "dist_adelaide": 104.929
 },
 {
  "id": "9",
  "name": "HS Bochum SolarCar-Team",
  "number": 11,
  "car_name": "Sun Riser",
  "country": "de",
  "class_id": 6,
  "lat": -34.11409,
  "lng": 138.18582,
  "gps_when": "2015-10-23 05:00:12",
  "trailered": 0,
  "dist_darwin": 2517.853,
  "dist_adelaide": 97.916
 },
 {
  "id": "9",
  "name": "HS Bochum SolarCar-Team",
  "number": 11,
  "car_name": "Sun Riser",
  "country": "de",
  "class_id": 6,
  "lat": -34.18486,
  "lng": 138.15353,
  "gps_when": "2015-10-23 05:10:09",
  "trailered": 0,
  "dist_darwin": 2524.337,
  "dist_adelaide": 92.019
 },
 {
  "id": "9",
  "name": "HS Bochum SolarCar-Team",
  "number": 11,
  "car_name": "Sun Riser",
  "country": "de",
  "class_id": 6,
  "lat": -34.23978,
  "lng": 138.21251,
  "gps_when": "2015-10-23 05:20:26",
  "trailered": 0,
  "dist_darwin": 2531.862,
  "dist_adelaide": 84.162
 },
 {
  "id": "9",
  "name": "HS Bochum SolarCar-Team",
  "number": 11,
  "car_name": "Sun Riser",
  "country": "de",
  "class_id": 6,
  "lat": -34.30302,
  "lng": 138.25053,
  "gps_when": "2015-10-23 05:30:14",
  "trailered": 0,
  "dist_darwin": 2539.641,
  "dist_adelaide": 76.317
 },
 {
  "id": "9",
  "name": "HS Bochum SolarCar-Team",
  "number": 11,
  "car_name": "Sun Riser",
  "country": "de",
  "class_id": 6,
  "lat": -34.34198,
  "lng": 138.28305,
  "gps_when": "2015-10-23 05:40:11",
  "trailered": 0,
  "dist_darwin": 2544.705,
  "dist_adelaide": 71.136
 },
 {
  "id": "9",
  "name": "HS Bochum SolarCar-Team",
  "number": 11,
  "car_name": "Sun Riser",
  "country": "de",
  "class_id": 6,
  "lat": -34.3419,
  "lng": 138.28302,
  "gps_when": "2015-10-23 05:50:07",
  "trailered": 0,
  "dist_darwin": 2544.695,
  "dist_adelaide": 71.145
 },
 {
  "id": "9",
  "name": "HS Bochum SolarCar-Team",
  "number": 11,
  "car_name": "Sun Riser",
  "country": "de",
  "class_id": 6,
  "lat": -34.34193,
  "lng": 138.28302,
  "gps_when": "2015-10-23 06:00:09",
  "trailered": 0,
  "dist_darwin": 2544.698,
  "dist_adelaide": 71.142
 },
 {
  "id": "9",
  "name": "HS Bochum SolarCar-Team",
  "number": 11,
  "car_name": "Sun Riser",
  "country": "de",
  "class_id": 6,
  "lat": -34.34195,
  "lng": 138.28302,
  "gps_when": "2015-10-23 06:10:39",
  "trailered": 0,
  "dist_darwin": 2544.701,
  "dist_adelaide": 71.14
 },
 {
  "id": "9",
  "name": "HS Bochum SolarCar-Team",
  "number": 11,
  "car_name": "Sun Riser",
  "country": "de",
  "class_id": 6,
  "lat": -34.34186,
  "lng": 138.28307,
  "gps_when": "2015-10-23 06:20:11",
  "trailered": 0,
  "dist_darwin": 2544.693,
  "dist_adelaide": 71.147
 },
 {
  "id": "9",
  "name": "HS Bochum SolarCar-Team",
  "number": 11,
  "car_name": "Sun Riser",
  "country": "de",
  "class_id": 6,
  "lat": -34.34195,
  "lng": 138.28302,
  "gps_when": "2015-10-23 06:30:04",
  "trailered": 0,
  "dist_darwin": 2544.701,
  "dist_adelaide": 71.14
 },
 {
  "id": "9",
  "name": "HS Bochum SolarCar-Team",
  "number": 11,
  "car_name": "Sun Riser",
  "country": "de",
  "class_id": 6,
  "lat": -34.39732,
  "lng": 138.31703,
  "gps_when": "2015-10-23 06:40:04",
  "trailered": 0,
  "dist_darwin": 2551.533,
  "dist_adelaide": 64.249
 },
 {
  "id": "9",
  "name": "HS Bochum SolarCar-Team",
  "number": 11,
  "car_name": "Sun Riser",
  "country": "de",
  "class_id": 6,
  "lat": -34.45927,
  "lng": 138.36378,
  "gps_when": "2015-10-23 06:50:06",
  "trailered": 0,
  "dist_darwin": 2559.438,
  "dist_adelaide": 56.224
 },
 {
  "id": "9",
  "name": "HS Bochum SolarCar-Team",
  "number": 11,
  "car_name": "Sun Riser",
  "country": "de",
  "class_id": 6,
  "lat": -34.51727,
  "lng": 138.41986,
  "gps_when": "2015-10-23 07:00:03",
  "trailered": 0,
  "dist_darwin": 2567.21,
  "dist_adelaide": 48.331
 },
 {
  "id": "9",
  "name": "HS Bochum SolarCar-Team",
  "number": 11,
  "car_name": "Sun Riser",
  "country": "de",
  "class_id": 6,
  "lat": -34.56752,
  "lng": 138.47844,
  "gps_when": "2015-10-23 07:10:05",
  "trailered": 0,
  "dist_darwin": 2574.247,
  "dist_adelaide": 41.335
 },
 {
  "id": "9",
  "name": "HS Bochum SolarCar-Team",
  "number": 11,
  "car_name": "Sun Riser",
  "country": "de",
  "class_id": 6,
  "lat": -34.62729,
  "lng": 138.52509,
  "gps_when": "2015-10-23 07:20:20",
  "trailered": 0,
  "dist_darwin": 2581.925,
  "dist_adelaide": 33.836
 },
 {
  "id": "9",
  "name": "HS Bochum SolarCar-Team",
  "number": 11,
  "car_name": "Sun Riser",
  "country": "de",
  "class_id": 6,
  "lat": -34.68871,
  "lng": 138.5627,
  "gps_when": "2015-10-23 07:30:25",
  "trailered": 0,
  "dist_darwin": 2589.504,
  "dist_adelaide": 26.494
 },
 {
  "id": "9",
  "name": "HS Bochum SolarCar-Team",
  "number": 11,
  "car_name": "Sun Riser",
  "country": "de",
  "class_id": 6,
  "lat": -34.73158,
  "lng": 138.58255,
  "gps_when": "2015-10-23 07:40:04",
  "trailered": 0,
  "dist_darwin": 2594.599,
  "dist_adelaide": 21.542
 },
 {
  "id": "9",
  "name": "HS Bochum SolarCar-Team",
  "number": 11,
  "car_name": "Sun Riser",
  "country": "de",
  "class_id": 6,
  "lat": -34.73195,
  "lng": 138.58525,
  "gps_when": "2015-10-23 07:50:03",
  "trailered": 0,
  "dist_darwin": 2594.72,
  "dist_adelaide": 21.478
 },
 {
  "id": "9",
  "name": "HS Bochum SolarCar-Team",
  "number": 11,
  "car_name": "Sun Riser",
  "country": "de",
  "class_id": 6,
  "lat": -34.73196,
  "lng": 138.58525,
  "gps_when": "2015-10-23 08:01:30",
  "trailered": 0,
  "dist_darwin": 2594.721,
  "dist_adelaide": 21.477
 },
 {
  "id": "9",
  "name": "HS Bochum SolarCar-Team",
  "number": 11,
  "car_name": "Sun Riser",
  "country": "de",
  "class_id": 6,
  "lat": -34.72604,
  "lng": 138.58073,
  "gps_when": "2015-10-23 22:38:31",
  "trailered": 0,
  "dist_darwin": 2593.963,
  "dist_adelaide": 22.171
 },
 {
  "id": "9",
  "name": "HS Bochum SolarCar-Team",
  "number": 11,
  "car_name": "Sun Riser",
  "country": "de",
  "class_id": 6,
  "lat": -34.72603,
  "lng": 138.58073,
  "gps_when": "2015-10-23 22:50:30",
  "trailered": 0,
  "dist_darwin": 2593.962,
  "dist_adelaide": 22.172
 },
 {
  "id": "9",
  "name": "HS Bochum SolarCar-Team",
  "number": 11,
  "car_name": "Sun Riser",
  "country": "de",
  "class_id": 6,
  "lat": -34.72606,
  "lng": 138.58075,
  "gps_when": "2015-10-23 22:57:44",
  "trailered": 0,
  "dist_darwin": 2593.966,
  "dist_adelaide": 22.168
 },
 {
  "id": "9",
  "name": "HS Bochum SolarCar-Team",
  "number": 11,
  "car_name": "Sun Riser",
  "country": "de",
  "class_id": 6,
  "lat": -34.72603,
  "lng": 138.58073,
  "gps_when": "2015-10-23 23:07:44",
  "trailered": 0,
  "dist_darwin": 2593.962,
  "dist_adelaide": 22.172
 },
 {
  "id": "9",
  "name": "HS Bochum SolarCar-Team",
  "number": 11,
  "car_name": "Sun Riser",
  "country": "de",
  "class_id": 6,
  "lat": -34.72601,
  "lng": 138.5807,
  "gps_when": "2015-10-23 23:17:49",
  "trailered": 0,
  "dist_darwin": 2593.959,
  "dist_adelaide": 22.174
 },
 {
  "id": "9",
  "name": "HS Bochum SolarCar-Team",
  "number": 11,
  "car_name": "Sun Riser",
  "country": "de",
  "class_id": 6,
  "lat": -34.72601,
  "lng": 138.5807,
  "gps_when": "2015-10-23 23:27:46",
  "trailered": 0,
  "dist_darwin": 2593.959,
  "dist_adelaide": 22.174
 },
 {
  "id": "9",
  "name": "HS Bochum SolarCar-Team",
  "number": 11,
  "car_name": "Sun Riser",
  "country": "de",
  "class_id": 6,
  "lat": -34.72603,
  "lng": 138.58075,
  "gps_when": "2015-10-23 23:38:18",
  "trailered": 0,
  "dist_darwin": 2593.963,
  "dist_adelaide": 22.172
 },
 {
  "id": "9",
  "name": "HS Bochum SolarCar-Team",
  "number": 11,
  "car_name": "Sun Riser",
  "country": "de",
  "class_id": 6,
  "lat": -34.72603,
  "lng": 138.58073,
  "gps_when": "2015-10-23 23:47:42",
  "trailered": 0,
  "dist_darwin": 2593.962,
  "dist_adelaide": 22.172
 },
 {
  "id": "9",
  "name": "HS Bochum SolarCar-Team",
  "number": 11,
  "car_name": "Sun Riser",
  "country": "de",
  "class_id": 6,
  "lat": -34.72603,
  "lng": 138.58073,
  "gps_when": "2015-10-23 23:57:50",
  "trailered": 0,
  "dist_darwin": 2593.962,
  "dist_adelaide": 22.172
 },
 {
  "id": "9",
  "name": "HS Bochum SolarCar-Team",
  "number": 11,
  "car_name": "Sun Riser",
  "country": "de",
  "class_id": 6,
  "lat": -34.72603,
  "lng": 138.58073,
  "gps_when": "2015-10-24 00:07:41",
  "trailered": 0,
  "dist_darwin": 2593.962,
  "dist_adelaide": 22.172
 },
 {
  "id": "9",
  "name": "HS Bochum SolarCar-Team",
  "number": 11,
  "car_name": "Sun Riser",
  "country": "de",
  "class_id": 6,
  "lat": -34.73143,
  "lng": 138.58246,
  "gps_when": "2015-10-24 00:17:43",
  "trailered": 0,
  "dist_darwin": 2594.581,
  "dist_adelaide": 21.559
 },
 {
  "id": "9",
  "name": "HS Bochum SolarCar-Team",
  "number": 11,
  "car_name": "Sun Riser",
  "country": "de",
  "class_id": 6,
  "lat": -34.77544,
  "lng": 138.59508,
  "gps_when": "2015-10-24 00:27:43",
  "trailered": 0,
  "dist_darwin": 2599.576,
  "dist_adelaide": 16.592
 },
 {
  "id": "9",
  "name": "HS Bochum SolarCar-Team",
  "number": 11,
  "car_name": "Sun Riser",
  "country": "de",
  "class_id": 6,
  "lat": -34.83661,
  "lng": 138.5994,
  "gps_when": "2015-10-24 00:37:42",
  "trailered": 0,
  "dist_darwin": 2606.12,
  "dist_adelaide": 9.784
 },
 {
  "id": "9",
  "name": "HS Bochum SolarCar-Team",
  "number": 11,
  "car_name": "Sun Riser",
  "country": "de",
  "class_id": 6,
  "lat": -34.87189,
  "lng": 138.60193,
  "gps_when": "2015-10-24 00:47:42",
  "trailered": 0,
  "dist_darwin": 2609.896,
  "dist_adelaide": 5.857
 },
 {
  "id": "9",
  "name": "HS Bochum SolarCar-Team",
  "number": 11,
  "car_name": "Sun Riser",
  "country": "de",
  "class_id": 6,
  "lat": -34.91084,
  "lng": 138.59918,
  "gps_when": "2015-10-24 00:58:29",
  "trailered": 0,
  "dist_darwin": 2613.898,
  "dist_adelaide": 1.631
 },
 {
  "id": "9",
  "name": "HS Bochum SolarCar-Team",
  "number": 11,
  "car_name": "Sun Riser",
  "country": "de",
  "class_id": 6,
  "lat": -34.91736,
  "lng": 138.59949,
  "gps_when": "2015-10-24 01:07:55",
  "trailered": 0,
  "dist_darwin": 2614.591,
  "dist_adelaide": 0.976
 },
 {
  "id": "9",
  "name": "HS Bochum SolarCar-Team",
  "number": 11,
  "car_name": "Sun Riser",
  "country": "de",
  "class_id": 6,
  "lat": -34.91742,
  "lng": 138.59924,
  "gps_when": "2015-10-24 01:18:04",
  "trailered": 0,
  "dist_darwin": 2614.59,
  "dist_adelaide": 0.984
 },
 {
  "id": "9",
  "name": "HS Bochum SolarCar-Team",
  "number": 11,
  "car_name": "Sun Riser",
  "country": "de",
  "class_id": 6,
  "lat": -34.91734,
  "lng": 138.59918,
  "gps_when": "2015-10-24 01:38:09",
  "trailered": 0,
  "dist_darwin": 2614.579,
  "dist_adelaide": 0.994
 },
 {
  "id": "9",
  "name": "HS Bochum SolarCar-Team",
  "number": 11,
  "car_name": "Sun Riser",
  "country": "de",
  "class_id": 6,
  "lat": -34.91762,
  "lng": 138.5992,
  "gps_when": "2015-10-24 01:49:29",
  "trailered": 0,
  "dist_darwin": 2614.609,
  "dist_adelaide": 0.968
 }
]