[
 {
  "id": "10",
  "name": "Jusolarteam",
  "number": 46,
  "car_name": "SOLBRITT",
  "country": "se",
  "class_id": 5,
  "lat": -19.65521,
  "lng": 134.18793,
  "gps_when": "2015-10-19 06:36:58",
  "dist_darwin": 875.335,
  "dist_adelaide": 1751.327,
  "gps_age": "7 mins 42 secs"
 },
 {
  "id": "10",
  "name": "Jusolarteam",
  "number": 46,
  "car_name": "SOLBRITT",
  "country": "se",
  "class_id": 5,
  "lat": -19.6577,
  "lng": 134.18913,
  "gps_when": "2015-10-19 07:16:56",
  "dist_darwin": 875.638,
  "dist_adelaide": 1751.029
 },
 {
  "id": "10",
  "name": "Jusolarteam",
  "number": 46,
  "car_name": "SOLBRITT",
  "country": "se",
  "class_id": 5,
  "lat": -19.65778,
  "lng": 134.18895,
  "gps_when": "2015-10-19 22:20:58",
  "dist_darwin": 875.639,
  "dist_adelaide": 1751.025
 },
 {
  "id": "10",
  "name": "Jusolarteam",
  "number": 46,
  "car_name": "SOLBRITT",
  "country": "se",
  "class_id": 5,
  "lat": -19.65749,
  "lng": 134.18768,
  "gps_when": "2015-10-19 22:29:54",
  "dist_darwin": 875.554,
  "dist_adelaide": 1751.087
 },
 {
  "id": "10",
  "name": "Jusolarteam",
  "number": 46,
  "car_name": "SOLBRITT",
  "country": "se",
  "class_id": 5,
  "lat": -19.75577,
  "lng": 134.19373,
  "gps_when": "2015-10-19 22:39:53",
  "dist_darwin": 885.758,
  "dist_adelaide": 1740.32
 },
 {
  "id": "10",
  "name": "Jusolarteam",
  "number": 46,
  "car_name": "SOLBRITT",
  "country": "se",
  "class_id": 5,
  "lat": -19.86955,
  "lng": 134.20459,
  "gps_when": "2015-10-19 22:49:59",
  "dist_darwin": 897.757,
  "dist_adelaide": 1727.762
 },
 {
  "id": "10",
  "name": "Jusolarteam",
  "number": 46,
  "car_name": "SOLBRITT",
  "country": "se",
  "class_id": 5,
  "lat": -19.98276,
  "lng": 134.21626,
  "gps_when": "2015-10-19 22:59:56",
  "dist_darwin": 909.751,
  "dist_adelaide": 1715.248
 },
 {
  "id": "10",
  "name": "Jusolarteam",
  "number": 46,
  "car_name": "SOLBRITT",
  "country": "se",
  "class_id": 5,
  "lat": -20.10529,
  "lng": 134.22014,
  "gps_when": "2015-10-19 23:12:31",
  "dist_darwin": 922.386,
  "dist_adelaide": 1701.923
 },
 {
  "id": "10",
  "name": "Jusolarteam",
  "number": 46,
  "car_name": "SOLBRITT",
  "country": "se",
  "class_id": 5,
  "lat": -20.18936,
  "lng": 134.22128,
  "gps_when": "2015-10-19 23:19:52",
  "dist_darwin": 931.008,
  "dist_adelaide": 1692.822
 },
 {
  "id": "10",
  "name": "Jusolarteam",
  "number": 46,
  "car_name": "SOLBRITT",
  "country": "se",
  "class_id": 5,
  "lat": -20.30455,
  "lng": 134.23091,
  "gps_when": "2015-10-19 23:29:51",
  "dist_darwin": 943.172,
  "dist_adelaide": 1680.153
 },
 {
  "id": "10",
  "name": "Jusolarteam",
  "number": 46,
  "car_name": "SOLBRITT",
  "country": "se",
  "class_id": 5,
  "lat": -20.41832,
  "lng": 134.24515,
  "gps_when": "2015-10-19 23:39:54",
  "dist_darwin": 955.394,
  "dist_adelaide": 1667.525
 },
 {
  "id": "10",
  "name": "Jusolarteam",
  "number": 46,
  "car_name": "SOLBRITT",
  "country": "se",
  "class_id": 5,
  "lat": -20.52612,
  "lng": 134.27264,
  "gps_when": "2015-10-19 23:49:50",
  "dist_darwin": 967.547,
  "dist_adelaide": 1655.209
 },
 {
  "id": "10",
  "name": "Jusolarteam",
  "number": 46,
  "car_name": "SOLBRITT",
  "country": "se",
  "class_id": 5,
  "lat": -20.61647,
  "lng": 134.22028,
  "gps_when": "2015-10-19 23:59:49",
  "dist_darwin": 974.748,
  "dist_adelaide": 1646.795
 },
 {
  "id": "10",
  "name": "Jusolarteam",
  "number": 46,
  "car_name": "SOLBRITT",
  "country": "se",
  "class_id": 5,
  "lat": -20.72766,
  "lng": 134.24098,
  "gps_when": "2015-10-20 00:09:49",
  "dist_darwin": 987.005,
  "dist_adelaide": 1634.289
 },
 {
  "id": "10",
  "name": "Jusolarteam",
  "number": 46,
  "car_name": "SOLBRITT",
  "country": "se",
  "class_id": 5,
  "lat": -20.83986,
  "lng": 134.24106,
  "gps_when": "2015-10-20 00:19:52",
  "dist_darwin": 998.577,
  "dist_adelaide": 1622.205
 }
]